Workbook

Sheet Bill Rates
A1: Onyx Accounting Group, LLC
A2: Average Bill Rates by Client — 2026
A3: 2026 standard rates per client, with July-2026 Harvest actuals alongside. The blend method on the Assumptions tab decides which average drives the model.
A5: Client Group | B5: Client / Entity | C5: CFO | D5: Controller | E5: Staff | F5: Jul-26 billable hrs | G5: Jul-26 billable $ | H5: Jul-26 effective $/hr
A6: Mohrschladt Entities | B6: 1402 Victory Lane LLC | C6: 250 | D6: 145 | E6: 95 | F6: 1.2 | G6: 222.5 | H6: =IF(N(F6)=0,"",G6/F6) -> 185.41667
B7: 3540 E Boot Track, LLC | C7: 250 | D7: 145 | E7: 95 | F7: 3 | G7: 393.5 | H7: =IF(N(F7)=0,"",G7/F7) -> 131.16667
B8: 4530 W. Flint, LLC | C8: 250 | D8: 145 | E8: 95 | F8: 2 | G8: 298.5 | H8: =IF(N(F8)=0,"",G8/F8) -> 149.25
B9: 7327 Tierra Buena LLC | C9: 250 | D9: 145 | E9: 95 | F9: 2.7 | G9: 365 | H9: =IF(N(F9)=0,"",G9/F9) -> 135.18519
B10: 15650 Northsight LLC | C10: 250 | D10: 145 | E10: 95 | F10: 2.3 | G10: 420 | H10: =IF(N(F10)=0,"",G10/F10) -> 182.6087
B11: Barrett Living Trust | C11: 250 | D11: 145 | E11: 95 | F11: 6.5 | G11: 617.5 | H11: =IF(N(F11)=0,"",G11/F11) -> 95
B12: Catalpa Industrial Park, Inc. | C12: 250 | D12: 145 | E12: 95 | F12: 7.7 | G12: 840 | H12: =IF(N(F12)=0,"",G12/F12) -> 109.09091
B13: Mohrschladt Capital, LP | C13: 250 | D13: 145 | E13: 95 | H13: =IF(N(F13)=0,"",G13/F13) | I13: no July time — dormant
B14: Mohrschladt Howarth Associates, Inc. | C14: 250 | D14: 145 | E14: 95 | F14: 2.7 | G14: 473.5 | H14: =IF(N(F14)=0,"",G14/F14) -> 175.37037
B15: NEWPORT CLASSIC CARS LLC | C15: 250 | D15: 145 | E15: 95 | F15: 1.2 | G15: 191.5 | H15: =IF(N(F15)=0,"",G15/F15) -> 159.58333
B16: Obsidian Real Estate | C16: 250 | D16: 145 | E16: 95 | F16: 10.2 | G16: 1201.5 | H16: =IF(N(F16)=0,"",G16/F16) -> 117.79412
B17: Paradise Village LLC | C17: 250 | D17: 145 | E17: 95 | F17: 1 | G17: 95 | H17: =IF(N(F17)=0,"",G17/F17) -> 95
B18: Rancho Industrial Park, Inc. | C18: 250 | D18: 145 | E18: 95 | F18: 9 | G18: 1010 | H18: =IF(N(F18)=0,"",G18/F18) -> 112.22222
A19: Tavasci Entities | B19: 7730 Evans, LLC | C19: 250 | D19: 145 | E19: 95 | F19: 2.1 | G19: 246 | H19: =IF(N(F19)=0,"",G19/F19) -> 117.14286
B20: 909 Main, LLC | C20: 250 | D20: 145 | E20: 95 | F20: 3 | G20: 393.5 | H20: =IF(N(F20)=0,"",G20/F20) -> 131.16667
B21: Capital Financial, LLC | C21: 250 | D21: 145 | E21: 95 | F21: 18.5 | G21: 2021 | H21: =IF(N(F21)=0,"",G21/F21) -> 109.24324
B22: DQCC | C22: 250 | D22: 145 | E22: 95 | F22: 1.1 | G22: 151 | H22: =IF(N(F22)=0,"",G22/F22) -> 137.27273
B23: Educational Services, LLC | C23: 250 | D23: 145 | E23: 95 | F23: 1.3 | G23: 325 | H23: =IF(N(F23)=0,"",G23/F23) -> 250
B24: Educational Services Holdings LLC | C24: 250 | D24: 145 | E24: 95 | F24: 7.9 | G24: 1386 | H24: =IF(N(F24)=0,"",G24/F24) -> 175.44304
B25: KAMM ADGT | C25: 250 | D25: 145 | E25: 95 | F25: 1.1 | G25: 151 | H25: =IF(N(F25)=0,"",G25/F25) -> 137.27273
B26: Tavasci Personal | C26: 250 | D26: 145 | E26: 95 | H26: =IF(N(F26)=0,"",G26/F26) | I26: no July time — dormant
B27: Edcuational Services Intermediate, LLC | C27: 250 | D27: 145 | E27: 95 | H27: =IF(N(F27)=0,"",G27/F27) | I27: no July time — dormant
B28: International Alliance Group LLC | C28: 250 | D28: 145 | E28: 95 | F28: 218.4 | G28: 31142.5 | H28: =IF(N(F28)=0,"",G28/F28) -> 142.59386
B29: Little Moo's | C29: 250 | D29: 145 | E29: 95 | F29: 3.3 | G29: 360 | H29: =IF(N(F29)=0,"",G29/F29) -> 109.09091
B30: T5 Family Holdings, LLC | C30: 250 | D30: 145 | E30: 95 | F30: 12 | G30: 1341.5 | H30: =IF(N(F30)=0,"",G30/F30) -> 111.79167
B31: Tavasci Brothers Motorsports | C31: 250 | D31: 145 | E31: 95 | F31: 2.6 | G31: 293.5 | H31: =IF(N(F31)=0,"",G31/F31) -> 112.88462
B32: TSCC54, LLC | C32: 250 | D32: 145 | E32: 95 | H32: =IF(N(F32)=0,"",G32/F32) | I32: no July time — dormant
B33: VVI 1017 | C33: 250 | D33: 145 | E33: 95 | F33: 3.1 | G33: 418.5 | H33: =IF(N(F33)=0,"",G33/F33) -> 135
B34: VVNS | C34: 250 | D34: 145 | E34: 95 | F34: 26.8 | G34: 6033.5 | H34: =IF(N(F34)=0,"",G34/F34) -> 225.1306
A35: BeckShar | B35: BeckShar Development | C35: 250 | D35: 175 | E35: 100 | F35: 11.8 | G35: 2275 | H35: =IF(N(F35)=0,"",G35/F35) -> 192.79661
B36: BeckShar LLC | F36: 5.7 | G36: 570 | H36: =IF(N(F36)=0,"",G36/F36) -> 100
B37: BeckShar Diamond Commercial | F37: 0.7 | G37: 70 | H37: =IF(N(F37)=0,"",G37/F37) -> 100
B38: BSD Contracting LLC | F38: 1 | G38: 100 | H38: =IF(N(F38)=0,"",G38/F38) -> 100
A39: Midwest | B39: Midwest Contracting, Inc | C39: 250 | D39: 185 | E39: 100 | F39: 66.1 | G39: 10360 | H39: =IF(N(F39)=0,"",G39/F39) -> 156.73222
B40: Eight Eleven | F40: 46.2 | G40: 6045 | H40: =IF(N(F40)=0,"",G40/F40) -> 130.84416
B41: Southwest Rentals | F41: 10 | G41: 1900 | H41: =IF(N(F41)=0,"",G41/F41) -> 190
A42: Individual Clients | B42: 1915 NORTH 16TH STREET, LLC | H42: =IF(N(F42)=0,"",G42/F42) | I42: no July time — dormant
B43: Amerisource | C43: 250 | D43: 145 | E43: 95 | F43: 35.1 | G43: 3982.5 | H43: =IF(N(F43)=0,"",G43/F43) -> 113.46154
B44: Bjerk Builders | C44: 250 | D44: 195 | E44: 105 | H44: =IF(N(F44)=0,"",G44/F44) | I44: no July time — dormant
B45: Broadcast Rentals | C45: 250 | D45: 160 | E45: 95 | H45: =IF(N(F45)=0,"",G45/F45) | I45: no July time — dormant
B46: Emmi D SalonSpa, LLC. | H46: =IF(N(F46)=0,"",G46/F46) | I46: no July time — dormant
B47: Foothills Reserve | F47: 2.5 | G47: 500 | H47: =IF(N(F47)=0,"",G47/F47) -> 200
B48: Fountain Hills Golf Carts | H48: =IF(N(F48)=0,"",G48/F48) | I48: no July time — dormant
B49: GAV Enterprises, Inc | C49: 250 | D49: 175 | E49: 95 | F49: 14.9 | G49: 1415.5 | H49: =IF(N(F49)=0,"",G49/F49) -> 95
B50: Kartes Leasing | C50: 250 | D50: 150 | E50: 95 | H50: =IF(N(F50)=0,"",G50/F50) | I50: no July time — dormant
B51: Monark Sports | H51: =IF(N(F51)=0,"",G51/F51) | I51: no July time — dormant
B52: Mountain Trade Supply, Inc | F52: 8.8 | G52: 1980 | H52: =IF(N(F52)=0,"",G52/F52) -> 225
B53: Preferred Renovations | C53: 250 | D53: 175 | E53: 95 | F53: 5 | G53: 738.5 | H53: =IF(N(F53)=0,"",G53/F53) -> 147.7
B54: Prestige Arms Worldwide | C54: 250 | D54: 150 | E54: 95 | H54: =IF(N(F54)=0,"",G54/F54) | I54: no July time — dormant
B55: Prime Solar USA | C55: 250 | D55: 185 | E55: 110 | F55: 9.3 | G55: 2240.5 | H55: =IF(N(F55)=0,"",G55/F55) -> 240.91398
B56: Return Textiles | C56: 250 | D56: 185 | E56: 115 | H56: =IF(N(F56)=0,"",G56/F56) | I56: no July time — dormant
B57: SW Art Glass | C57: 250 | D57: 175 | E57: 95 | F57: 2.5 | G57: 625 | H57: =IF(N(F57)=0,"",G57/F57) -> 250
B58: Young Wealth Management | C58: 250 | D58: 175 | E58: 95 | F58: 5.3 | G58: 503.5 | H58: =IF(N(F58)=0,"",G58/F58) -> 95
A59: New in Harvest | B59: VV1012 LLC | F59: 40.3 | G59: 6782.5 | H59: =IF(N(F59)=0,"",G59/F59) -> 168.30025 | I59: logged time in July but has no 2026 rate — price this client
B60: Building and Development Professionals LLC | F60: 15 | G60: 3375 | H60: =IF(N(F60)=0,"",G60/F60) -> 225 | I60: logged time in July but has no 2026 rate — price this client
B61: Priced clients in average: =COUNT(C6:C58) | C61: =COUNT(C6:C58) -> 42
B62: Simple average — every priced client counts once | C62: =AVERAGE(C6:C60) -> 250 | D62: =AVERAGE(D6:D60) -> 153.21429 | E62: =AVERAGE(E6:E60) -> 96.309524 | I62: METHOD 1 — a 1-hour client counts as much as a 218-hour client
B63: Priced clients in the simple average | C63: =COUNT(C6:C60) -> 42 | I63: of which some logged no July time at all — see column I above
B65: Hours-weighted average — weighted by July billable hours | C65: =IFERROR(SUMPRODUCT((C6:C60)*(F6:F60))/SUMPRODUCT((C6:C60<>"")*(F6:F60)),0) -> 250 | D65: =IFERROR(SUMPRODUCT((D6:D60)*(F6:F60))/SUMPRODUCT((D6:D60<>"")*(F6:F60)),0) -> 153.39025 | E65: =IFERROR(SUMPRODUCT((E6:E60)*(F6:F60))/SUMPRODUCT((E6:E60<>"")*(F6:F60)),0) -> 96.056521 | I65: METHOD 2 — big clients dominate, dormant clients drop out
B67: CALIBRATION TO JULY ACTUALS
A68: basis 1 → | B68: July billable hours / billable $ (all clients) | F68: =SUM(F6:F60) -> 630.9 | G68: =SUM(G6:G60) -> 93854.5 | H68: =IFERROR(G68/F68,0) -> 148.76288 | I68: BASIS 1 — standard value of July time at the rates entered in Harvest
A69: basis 2 → | B69: Implied by actual Jan–Jul collections | F69: =F68*7 -> 4416.3 | G69: =SUM('Forecast 2026'!$B$11:$H$11) -> 690796.75 | H69: =IFERROR(G69/F69,0) -> 156.4198 | I69: BASIS 2 — seven months of actual cash sales over seven months of July-level billable hours. Higher than basis 1 because fixed-fee work collects more than the standard time value.
B70: Model blended rate at the simple-average card | H70: =IFERROR((('Monthly Capacity'!$N$22+'Monthly Capacity'!$N$23)*C62+'Monthly Capacity'!$N$24*D62+('Monthly Capacity'!$N$25+'Monthly Capacity'!$N$26+'Monthly Capacity'!$N$27)*E62)/'Monthly Capacity'!$N$28,0) -> 158.59492 | I70: the same hours mix priced at the rate card — uses the SIMPLE average, never the live rates, so there is no circular reference
B71: Calibration basis (1, 2 or 3) → realization factor | C71: 2 | H71: =IFERROR(CHOOSE($C$71,H68/H70,H69/H70,1),1) -> 0.98628503 | I71: 1 = standard time value · 2 = actual collections (default) · 3 = no calibration
B72: Calibrated rates — card × realization factor | C72: =C62*$H$71 -> 246.57126 | D72: =D62*$H$71 -> 151.11296 | E72: =E62*$H$71 -> 94.988641 | I72: METHOD 3 — scales the whole card so the model reproduces reality per billable hour
B73: • Weighting the rate card by hours barely moves it (method 1 vs 2 differ by well under a dollar) because the card is nearly uniform — every CFO rate is $250 and almost every staff rate is $95.
B74: • The real gap is ROLE MIX, not client weighting. July's actual $148.76/hr against the card's $158.59 blend says less of the firm's time is billed at CFO rates than the model assumes.
B75: • To weight properly by role, pull the Harvest report grouped by PERSON (or person x client) and enter hours by role. Until then method 3 calibrates the whole card to observed revenue per hour.
B76: • July invoiced $55,385 against $93,855 of billable work. If that is invoice timing it will wash out; if it is write-downs the effective rate is lower still. Worth confirming before locking a rate.

Sheet Assumptions
A1: Onyx Accounting Group, LLC
A2: Assumptions & Drivers
A3: Change any yellow cell to re-forecast the whole model.
A5: TIME & UTILIZATION
A6: Hours per week | B6: 40 | C6: Firm standard schedule
A7: Weeks per month | B7: 4 | C7: Legacy flat convention — superseded by the Monthly Capacity calendar
A8: Gross working hours per month | B8: =B6*B7 -> 160 | C8: 40 × 4 = 160 (flat). Real calendar averages 169.3 hrs/mo
A9: Non-billable admin hours per month | B9: 20 | C9: Per your spec
A10: Billable-eligible hours per month | B10: =B8-B9 -> 140 | C10: Flat basis only — superseded by Monthly Capacity
A11: PTO hours per year | B11: 80 | C11: 2 weeks — Onyx Handbook
A12: Paid holiday hours per year | B12: 56 | C12: 7 holidays × 8 hrs — Onyx Handbook
A13: PTO + holiday per month | B13: =(B11+B12)/12 -> 11.333333 | C13: Flat basis only — Monthly Capacity handles PTO and holidays by month
A14: Available billable hrs / mo (100% util) | B14: =B10-B13 -> 128.66667 | C14: Flat basis only — superseded by Monthly Capacity
A15: Utilization % — firm default | B15: 0.91 | C15: Starting point for every person. Override per person in Monthly Capacity column T.
A16: Paid hours per year (full-time) | B16: ='Monthly Capacity'!$N$14 -> 2088 | C16: Weekdays × 8 from the 2026 calendar (2,088) — divisor for hourly pay & loaded cost
A17: ↑ flat-basis block above is legacy; Monthly Capacity is the live driver
A18: EMPLOYER PAYROLL TAXES (AZ / US)
A19: Social Security — employer rate | B19: 0.062 | C19: FICA OASDI, capped at wage base
A20: Social Security wage base (2026) | B20: 184500 | C20: 2026 SSA max
A21: Medicare — employer rate | B21: 0.0145 | C21: Uncapped
A22: FUTA rate | B22: 0.006 | C22: Federal unemployment (net)
A23: FUTA wage base | B23: 7000 | C23: First $7,000 of wages
A24: AZ SUTA rate | B24: 0.0139 | C24: Arizona unemployment — set to your rate
A25: AZ SUTA wage base | B25: 8000 | C25: First $8,000 of wages (AZ 2026)
A27: OWNER COMPENSATION
A28: Owner (Steven) annual salary | B28: 184500 | C28: Set to Social Security wage-base max
A29: Owner client (billable) share | B29: 0.5 | C29: 50% client / 50% admin per your split
A30: Owner admin (overhead) share | B30: =1-B29 -> 0.5 | C30: flows to Operating Expenses
A32: BLENDED BILL RATES — 2026 (from Bill Rates tab)
A33: CFO average bill rate | B33: =CHOOSE($B$36,'Bill Rates'!$C$62,'Bill Rates'!$C$65,'Bill Rates'!$C$72) -> 246.57126 | C33: Steven, Lisa — follows the method in B36
A34: Controller average bill rate | B34: =CHOOSE($B$36,'Bill Rates'!$D$62,'Bill Rates'!$D$65,'Bill Rates'!$D$72) -> 151.11296 | C34: Jessica — follows the method in B36
A35: Staff average bill rate | B35: =CHOOSE($B$36,'Bill Rates'!$E$62,'Bill Rates'!$E$65,'Bill Rates'!$E$72) -> 94.988641 | C35: Christine, Valentina, Josephine — follows the method in B36
A36: Rate blend method (1, 2 or 3) | B36: 3 | C36: 1 = simple average · 2 = hours-weighted · 3 = calibrated to July actuals
A38: OWNER HOURS MODE (1 or 2) | B38: 1 | C38: 1 = fixed 50% share (today) · 2 = residual to hit a net-income target
A40: BONUS FACTOR SOURCE (1 or 2) | B40: 1 | C40: 1 = the manual quarterly factors · 2 = the earned scorecard factor

Sheet Staff P&L
A1: Onyx Accounting Group, LLC
A2: Staff P&L — Pay, Labor Burden & Gross Profit per Person
A3: Blue = input. Loaded hourly cost = full burden (pay + AZ/US tax + PEO benefits) ÷ paid hours (2,088 from the 2026 calendar). Hours & revenue now come from the Monthly Capacity tab.
D4: COMPENSATION & EMPLOYER BURDEN | P4: HOURS, REVENUE & GROSS PROFIT
A5: Employee | B5: Role | C5: Pay basis | D5: Pay rate / salary | E5: Base annual comp | F5: Empl. SS | G5: Empl. Medicare | H5: FUTA | I5: AZ SUTA | J5: Total empl. tax | K5: Benefits $/mo (2026 avg) | L5: Benefits annual | M5: Fully-loaded annual cost (incl. bonus) | N5: Loaded cost /mo | O5: Loaded cost /hr | P5: Billable hrs /yr | Q5: Billable hrs /mo (avg) | R5: Bill rate | S5: Revenue /mo | T5: COGS alloc % | U5: COGS cost /mo | V5: OpEx cost /mo | W5: Gross profit /mo | X5: GP margin
A6: Steven Nikolov | B6: CFO | C6: Salary (owner) | D6: =Assumptions!$B$28 -> 184500 | E6: =D6 -> 184500 | F6: =Assumptions!$B$19*MIN(E6,Assumptions!$B$20) -> 11439 | G6: =Assumptions!$B$21*E6 -> 2675.25 | H6: =Assumptions!$B$22*MIN(E6,Assumptions!$B$23) -> 42 | I6: =Assumptions!$B$24*MIN(E6,Assumptions!$B$25) -> 111.2 | J6: =SUM(F6:I6) -> 14267.45 | K6: =Benefits!$G$19 -> 345.24833 | L6: =K6*12 -> 4142.98 | M6: =E6+J6+L6+J18 -> 202910.43 | N6: =M6/12 -> 16909.202 | O6: =M6/Assumptions!$B$16 -> 97.179325 | P6: ='Monthly Capacity'!$N$22 -> 888.16 | Q6: =P6/12 -> 74.013333 | R6: =Assumptions!$B$33 -> 246.57126 | S6: ='Monthly Capacity'!$N$31/12 -> 18249.561 | T6: =IF(Assumptions!$B$38=2,IFERROR(MIN(1,'Monthly Capacity'!$N$22/('Monthly Capacity'!$N$13-'Monthly Capacity'!$P$22*12-'Monthly Capacity'!$R$22)),0),Assumptions!$B$29) -> 0.5 | U6: =N6*T6 -> 8454.6012 | V6: =N6*(1-T6) -> 8454.6012 | W6: =S6-U6 -> 9794.9594 | X6: =IF(S6=0,0,W6/S6) -> 0.53672302
A7: Lisa Danforth | B7: CFO | C7: Salary | D7: 176000 | E7: =D7 -> 176000 | F7: =Assumptions!$B$19*MIN(E7,Assumptions!$B$20) -> 10912 | G7: =Assumptions!$B$21*E7 -> 2552 | H7: =Assumptions!$B$22*MIN(E7,Assumptions!$B$23) -> 42 | I7: =Assumptions!$B$24*MIN(E7,Assumptions!$B$25) -> 111.2 | J7: =SUM(F7:I7) -> 13617.2 | K7: =Benefits!$G$20 -> 341.70667 | L7: =K7*12 -> 4100.48 | M7: =E7+J7+L7+J19 -> 193717.68 | N7: =M7/12 -> 16143.14 | O7: =M7/Assumptions!$B$16 -> 92.776667 | P7: ='Monthly Capacity'!$N$23 -> 1557.92 | Q7: =P7/12 -> 129.82667 | R7: =Assumptions!$B$33 -> 246.57126 | S7: ='Monthly Capacity'!$N$32/12 -> 32011.524 | T7: 1 | U7: =N7*T7 -> 16143.14 | V7: =N7*(1-T7) -> 0 | W7: =S7-U7 -> 15868.384 | X7: =IF(S7=0,0,W7/S7) -> 0.49570849
A8: Jessica Bumphus | B8: Controller | C8: Hourly | D8: 60 | E8: =D8*Assumptions!$B$16 -> 125280 | F8: =Assumptions!$B$19*MIN(E8,Assumptions!$B$20) -> 7767.36 | G8: =Assumptions!$B$21*E8 -> 1816.56 | H8: =Assumptions!$B$22*MIN(E8,Assumptions!$B$23) -> 42 | I8: =Assumptions!$B$24*MIN(E8,Assumptions!$B$25) -> 111.2 | J8: =SUM(F8:I8) -> 9737.12 | K8: =Benefits!$G$21 -> 236.05167 | L8: =K8*12 -> 2832.62 | M8: =E8+J8+L8+J20 -> 137849.74 | N8: =M8/12 -> 11487.478 | O8: =M8/Assumptions!$B$16 -> 66.01999 | P8: ='Monthly Capacity'!$N$24 -> 1557.92 | Q8: =P8/12 -> 129.82667 | R8: =Assumptions!$B$34 -> 151.11296 | S8: ='Monthly Capacity'!$N$33/12 -> 19618.491 | T8: 1 | U8: =N8*T8 -> 11487.478 | V8: =N8*(1-T8) -> 0 | W8: =S8-U8 -> 8131.013 | X8: =IF(S8=0,0,W8/S8) -> 0.41445659
A9: Christine Johnson | B9: Staff | C9: Hourly | D9: 40 | E9: =D9*Assumptions!$B$16 -> 83520 | F9: =Assumptions!$B$19*MIN(E9,Assumptions!$B$20) -> 5178.24 | G9: =Assumptions!$B$21*E9 -> 1211.04 | H9: =Assumptions!$B$22*MIN(E9,Assumptions!$B$23) -> 42 | I9: =Assumptions!$B$24*MIN(E9,Assumptions!$B$25) -> 111.2 | J9: =SUM(F9:I9) -> 6542.48 | K9: =Benefits!$G$22 -> 119.78833 | L9: =K9*12 -> 1437.46 | M9: =E9+J9+L9+J21 -> 94197.218 | N9: =M9/12 -> 7849.7682 | O9: =M9/Assumptions!$B$16 -> 45.11361 | P9: ='Monthly Capacity'!$N$25 -> 1557.92 | Q9: =P9/12 -> 129.82667 | R9: =Assumptions!$B$35 -> 94.988641 | S9: ='Monthly Capacity'!$N$34/12 -> 12332.059 | T9: 1 | U9: =N9*T9 -> 7849.7682 | V9: =N9*(1-T9) -> 0 | W9: =S9-U9 -> 4482.2905 | X9: =IF(S9=0,0,W9/S9) -> 0.36346652
A10: Valentina Dikova | B10: Staff | C10: Contractor (BG) | D10: 4200 | E10: =D10*12 -> 50400 | F10: 0 | G10: 0 | H10: 0 | I10: 0 | J10: =SUM(F10:I10) -> 0 | K10: =Benefits!$G$23 -> 0 | L10: =K10*12 -> 0 | M10: =E10+J10+L10+J22 -> 50400 | N10: =M10/12 -> 4200 | O10: =M10/Assumptions!$B$16 -> 24.137931 | P10: ='Monthly Capacity'!$N$26 -> 1630.72 | Q10: =P10/12 -> 135.89333 | R10: =Assumptions!$B$35 -> 94.988641 | S10: ='Monthly Capacity'!$N$35/12 -> 12908.323 | T10: 1 | U10: =N10*T10 -> 4200 | V10: =N10*(1-T10) -> 0 | W10: =S10-U10 -> 8708.3231 | X10: =IF(S10=0,0,W10/S10) -> 0.67462853
A11: Josephine Mack | B11: Admin/Staff | C11: Salary | D11: 80000 | E11: =D11 -> 80000 | F11: =Assumptions!$B$19*MIN(E11,Assumptions!$B$20) -> 4960 | G11: =Assumptions!$B$21*E11 -> 1160 | H11: =Assumptions!$B$22*MIN(E11,Assumptions!$B$23) -> 42 | I11: =Assumptions!$B$24*MIN(E11,Assumptions!$B$25) -> 111.2 | J11: =SUM(F11:I11) -> 6273.2 | K11: =Benefits!$G$24 -> 118.32167 | L11: =K11*12 -> 1419.86 | M11: =E11+J11+L11+J23 -> 104055.86 | N11: =M11/12 -> 8671.3217 | O11: =M11/Assumptions!$B$16 -> 49.835182 | P11: ='Monthly Capacity'!$N$27 -> 266.448 | Q11: =P11/12 -> 22.204 | R11: =Assumptions!$B$35 -> 94.988641 | S11: ='Monthly Capacity'!$N$36/12 -> 2109.1278 | T11: 0.15 | U11: =N11*T11 -> 1300.6982 | V11: =N11*(1-T11) -> 7370.6234 | W11: =S11-U11 -> 808.42954 | X11: =IF(S11=0,0,W11/S11) -> 0.38330041
A12: TOTAL / FIRM | E12: =SUM(E6:E11) -> 699700 | F12: =SUM(F6:F11) -> 40256.6 | G12: =SUM(G6:G11) -> 9414.85 | H12: =SUM(H6:H11) -> 210 | I12: =SUM(I6:I11) -> 556 | J12: =SUM(J6:J11) -> 50437.45 | K12: =SUM(K6:K11) -> 1161.1167 | L12: =SUM(L6:L11) -> 13933.4 | ... N12: =SUM(N6:N11) -> 65260.911 | O12: =M12/Assumptions!$B$16 -> 375.06271 | P12: =SUM(P6:P11) -> 7459.088 | Q12: =SUM(Q6:Q11) -> 621.59067 | S12: =SUM(S6:S11) -> 97229.086 | U12: =SUM(U6:U11) -> 49435.686 | V12: =SUM(V6:V11) -> 15825.225 | W12: =SUM(W6:W11) -> 47793.4 | X12: =IF(S12=0,0,W12/S12) -> 0.49155455
A15: QUARTERLY DISCRETIONARY BONUS | K15: Owner is excluded by policy — set his target to 0%.
A16: Discretionary payout factor | D16: 0 | E16: 0 | F16: 2 | G16: 2 | K16: ← the discretionary lever: 0% pays nothing that quarter, 150% pays one-and-a-half target.
A17: Employee | B17: Target % of base | C17: Annual target | D17: Q1 (Mar) | E17: Q2 (Jun) | F17: Q3 (Sep) | G17: Q4 (Dec) | H17: Annual bonus | I17: Empl. tax on bonus | J17: Total bonus cost
A18: =A6 -> Steven Nikolov | B18: 0 | C18: =E6*B18 -> 0 | D18: =$C18/4*D$16 -> 0 | E18: =$C18/4*E$16 -> 0 | F18: =$C18/4*F$16 -> 0 | G18: =$C18/4*G$16 -> 0 | H18: =SUM(D18:G18) -> 0 | I18: =Assumptions!$B$19*MIN(H18,MAX(0,Assumptions!$B$20-E6))+Assumptions!$B$21*H18 -> 0 | J18: =H18+I18 -> 0
A19: =A7 -> Lisa Danforth | B19: 0 | C19: =E7*B19 -> 0 | D19: =$C19/4*IF(Assumptions!$B$40=2,IF(D$16>0,$H$42,0),D$16) -> 0 | E19: =$C19/4*IF(Assumptions!$B$40=2,IF(E$16>0,$H$42,0),E$16) -> 0 | F19: =$C19/4*IF(Assumptions!$B$40=2,IF(F$16>0,$H$42,0),F$16) -> 0 | G19: =$C19/4*IF(Assumptions!$B$40=2,IF(G$16>0,$H$42,0),G$16) -> 0 | H19: =SUM(D19:G19) -> 0 | I19: =Assumptions!$B$19*MIN(H19,MAX(0,Assumptions!$B$20-E7))+Assumptions!$B$21*H19 -> 0 | J19: =H19+I19 -> 0
A20: =A8 -> Jessica Bumphus | B20: 0 | C20: =E8*B20 -> 0 | D20: =$C20/4*IF(Assumptions!$B$40=2,IF(D$16>0,$I$42,0),D$16) -> 0 | E20: =$C20/4*IF(Assumptions!$B$40=2,IF(E$16>0,$I$42,0),E$16) -> 0 | F20: =$C20/4*IF(Assumptions!$B$40=2,IF(F$16>0,$I$42,0),F$16) -> 0 | G20: =$C20/4*IF(Assumptions!$B$40=2,IF(G$16>0,$I$42,0),G$16) -> 0 | H20: =SUM(D20:G20) -> 0 | I20: =Assumptions!$B$19*MIN(H20,MAX(0,Assumptions!$B$20-E8))+Assumptions!$B$21*H20 -> 0 | J20: =H20+I20 -> 0
A21: =A9 -> Christine Johnson | B21: 0.03 | C21: =E9*B21 -> 2505.6 | D21: =$C21/4*IF(Assumptions!$B$40=2,IF(D$16>0,$J$42,0),D$16) -> 0 | E21: =$C21/4*IF(Assumptions!$B$40=2,IF(E$16>0,$J$42,0),E$16) -> 0 | F21: =$C21/4*IF(Assumptions!$B$40=2,IF(F$16>0,$J$42,0),F$16) -> 1252.8 | G21: =$C21/4*IF(Assumptions!$B$40=2,IF(G$16>0,$J$42,0),G$16) -> 1252.8 | H21: =SUM(D21:G21) -> 2505.6 | I21: =Assumptions!$B$19*MIN(H21,MAX(0,Assumptions!$B$20-E9))+Assumptions!$B$21*H21 -> 191.6784 | J21: =H21+I21 -> 2697.2784
A22: =A10 -> Valentina Dikova | B22: 0 | C22: =E10*B22 -> 0 | D22: =$C22/4*D$16 -> 0 | E22: =$C22/4*E$16 -> 0 | F22: =$C22/4*F$16 -> 0 | G22: =$C22/4*G$16 -> 0 | H22: =SUM(D22:G22) -> 0 | I22: 0 | J22: =H22+I22 -> 0
A23: =A11 -> Josephine Mack | B23: 0.19 | C23: =E11*B23 -> 15200 | D23: =$C23/4*D$16 -> 0 | E23: =$C23/4*E$16 -> 0 | F23: =$C23/4*F$16 -> 7600 | G23: =$C23/4*G$16 -> 7600 | H23: =SUM(D23:G23) -> 15200 | I23: =Assumptions!$B$19*MIN(H23,MAX(0,Assumptions!$B$20-E11))+Assumptions!$B$21*H23 -> 1162.8 | J23: =H23+I23 -> 16362.8
A24: TOTAL BONUS (all) | C24: =SUM(C18:C23) -> 17705.6 | D24: =SUM(D18:D23) -> 0 | E24: =SUM(E18:E23) -> 0 | F24: =SUM(F18:F23) -> 8852.8 | G24: =SUM(G18:G23) -> 8852.8 | H24: =SUM(H18:H23) -> 17705.6 | I24: =SUM(I18:I23) -> 1354.4784 | J24: =SUM(J18:J23) -> 19060.078
A25: of which W-2 payroll → Budget P&L | C25: =C18+C19+C20+C21+C23 -> 17705.6 | D25: =D18+D19+D20+D21+D23 -> 0 | E25: =E18+E19+E20+E21+E23 -> 0 | F25: =F18+F19+F20+F21+F23 -> 8852.8 | G25: =G18+G19+G20+G21+G23 -> 8852.8 | H25: =H18+H19+H20+H21+H23 -> 17705.6 | I25: =I18+I19+I20+I21+I23 -> 1354.4784 | J25: =J18+J19+J20+J21+J23 -> 19060.078
A26: of which contractor → Cost of labor | C26: =C22 -> 0 | D26: =D22 -> 0 | E26: =E22 -> 0 | F26: =F22 -> 0 | G26: =G22 -> 0 | H26: =H22 -> 0 | I26: =I22 -> 0 | J26: =J22 -> 0
A28: • Bonuses are paid in March, June, September and December. Quarterly amount = annual target ÷ 4 × that quarter's payout factor.
A29: • Fully-loaded annual cost in column M includes the bonus and its employer tax, so loaded cost per hour and gross profit per person already reflect the plan.
A30: • The Budget P&L 'Discretionary Bonuses' line and the employer tax on it are driven by the W-2 subtotal. On Forecast 2026 only the September and December payments land in the budget months — March and June are inside the Jan–Jul actuals.
A31: • Valentina is a contractor, so her bonus is not payroll. It sits inside her fully-loaded cost and reaches the P&L through 'Cost of labor - Contractors', spread evenly across the months rather than in four payments. The annual amount is the same either way.
A32: • For reference, actual bonuses paid Jan–Jul 2026 were $2,610 for the whole firm — the 5% target here is a placeholder, so set each person's target before relying on the numbers.
A34: OPERATIONAL BONUS SCORECARD — earns the payout factor instead of typing it
A35: Set the KPI actuals each quarter; the factor is earned. Switch Assumptions!B40 to 2 to let this drive the bonus instead of the manual factors above.
A36: KPI | B36: Direction | C36: Threshold (50%) | D36: Target (100%) | E36: Stretch (150%) | F36: Actual | G36: Earned multiplier | H36: Weight Lisa | I36: Weight Jessica | J36: Weight Christine
A37: Personal billable hours vs the Monthly Capacity plan | B37: higher | C37: 0.85 | D37: 1 | E37: 1.1 | F37: 0.97 | G37: =IF((F37-C37)/(D37-C37)<0,0,IF((F37-D37)/(E37-D37)<0,0.5+0.5*(F37-C37)/(D37-C37),MIN(1.5,1+0.5*(F37-D37)/(E37-D37)))) -> 0.9 | H37: 0.3 | I37: 0.4 | J37: 0.55 | K37: Harvest hours ÷ that person's plan hours. July firm-wide came in at 97% of plan.
A38: Realized revenue per billable hour (3-month average) | B38: higher | C38: 145 | D38: 158 | E38: 170 | F38: 156.42 | G38: =IF((F38-C38)/(D38-C38)<0,0,IF((F38-D38)/(E38-D38)<0,0.5+0.5*(F38-C38)/(D38-C38),MIN(1.5,1+0.5*(F38-D38)/(E38-D38)))) -> 0.93923077 | H38: 0.3 | I38: 0.25 | J38: 0.15 | K38: Collections ÷ billable hours, lagged so it is not gamed by a single month.
A39: Days from work performed to invoice sent | B39: lower | C39: 45 | D39: 30 | E39: 20 | F39: 35 | G39: =IF((F39-C39)/(D39-C39)<0,0,IF((F39-D39)/(E39-D39)<0,0.5+0.5*(F39-C39)/(D39-C39),MIN(1.5,1+0.5*(F39-D39)/(E39-D39)))) -> 0.83333333 | H39: 0.15 | I39: 0.2 | J39: 0.2 | K39: The one metric that fixes the invoice lag. Needs a Harvest/QBO date report.
A40: Net revenue retention on the clients they own | B40: higher | C40: 0.95 | D40: 1.05 | E40: 1.15 | F40: 1 | G40: =IF((F40-C40)/(D40-C40)<0,0,IF((F40-D40)/(E40-D40)<0,0.5+0.5*(F40-C40)/(D40-C40),MIN(1.5,1+0.5*(F40-D40)/(E40-D40)))) -> 0.75 | H40: 0.25 | I40: 0.15 | J40: 0.1 | K40: This year's fees ÷ last year's, same client group. Set the groups first.
A41: Total weight — each column must add to 100% | H41: =SUM(H37:H40) -> 1 | I41: =SUM(I37:I40) -> 1 | J41: =SUM(J37:J40) -> 1 | K41: =IF(AND(ROUND(H41,4)=1,ROUND(I41,4)=1,ROUND(J41,4)=1),"weights OK","FIX — each weight column must total 100%") -> weights OK
A42: EARNED PAYOUT FACTOR | H42: =SUMPRODUCT($G$37:$G$40,H37:H40) -> 0.86426923 | I42: =SUMPRODUCT($G$37:$G$40,I37:I40) -> 0.87397436 | J42: =SUMPRODUCT($G$37:$G$40,J37:J40) -> 0.87755128
A44: RECOMMENDED TARGET BONUS % OF BASE
A45: Lisa Danforth (CFO) | C45: 0.12 | K45: owns client relationships and pricing — most leverage
A46: Jessica Bumphus (Controller) | C46: 0.1 | K46: owns delivery and the close calendar
A47: Christine Johnson (Staff) | C47: 0.06 | K47: owns her own hours and turnaround
A48: Josephine Mack (Admin) | C48: 0.1 | K48: see the pay options below
A49: Valentina Dikova (contractor) | C49: 0 | K49: contractor — pay through the contract, not a bonus plan
A50: Steven Nikolov (owner) | C50: 0 | K50: excluded by policy — the owner takes profit, not bonus
A51: Copy the ones you accept into the Target % column (B18:B23) above.
A53: JOSEPHINE — PAY OPTIONS ($80,000 today; she asked for $90–110k)
A54: Option | B54: Base | C54: Bonus at target | D54: Cash at target | E54: Employer tax | F54: Loaded cost | G54: vs today
A55: Today — $80k, no bonus | B55: 80000 | C55: 0 | D55: =B55+C55 -> 80000 | E55: =Assumptions!$B$19*MIN(D55,Assumptions!$B$20)+Assumptions!$B$21*D55+Assumptions!$B$22*MIN(D55,Assumptions!$B$23)+Assumptions!$B$24*MIN(D55,Assumptions!$B$25) -> 6273.2 | F55: =D55+E55 -> 86273.2 | G55: =F55-$F$55 -> 0
A56: A1 base $90,000 | B56: 90000 | C56: 0 | D56: =B56+C56 -> 90000 | E56: =Assumptions!$B$19*MIN(D56,Assumptions!$B$20)+Assumptions!$B$21*D56+Assumptions!$B$22*MIN(D56,Assumptions!$B$23)+Assumptions!$B$24*MIN(D56,Assumptions!$B$25) -> 7038.2 | F56: =D56+E56 -> 97038.2 | G56: =F56-$F$55 -> 10765 | K56: simple, permanent, no upside
A57: A2 base $95,000 | B57: 95000 | C57: 0 | D57: =B57+C57 -> 95000 | E57: =Assumptions!$B$19*MIN(D57,Assumptions!$B$20)+Assumptions!$B$21*D57+Assumptions!$B$22*MIN(D57,Assumptions!$B$23)+Assumptions!$B$24*MIN(D57,Assumptions!$B$25) -> 7420.7 | F57: =D57+E57 -> 102420.7 | G57: =F57-$F$55 -> 16147.5
A58: A3 base $100,000 | B58: 100000 | C58: 0 | D58: =B58+C58 -> 100000 | E58: =Assumptions!$B$19*MIN(D58,Assumptions!$B$20)+Assumptions!$B$21*D58+Assumptions!$B$22*MIN(D58,Assumptions!$B$23)+Assumptions!$B$24*MIN(D58,Assumptions!$B$25) -> 7803.2 | F58: =D58+E58 -> 107803.2 | G58: =F58-$F$55 -> 21530
A59: A4 base $110,000 | B59: 110000 | C59: 0 | D59: =B59+C59 -> 110000 | E59: =Assumptions!$B$19*MIN(D59,Assumptions!$B$20)+Assumptions!$B$21*D59+Assumptions!$B$22*MIN(D59,Assumptions!$B$23)+Assumptions!$B$24*MIN(D59,Assumptions!$B$25) -> 8568.2 | F59: =D59+E59 -> 118568.2 | G59: =F59-$F$55 -> 32295 | K59: top of her ask
A60: B $80k + $15,000 bonus | B60: 80000 | C60: 15000 | D60: =B60+C60 -> 95000 | E60: =Assumptions!$B$19*MIN(D60,Assumptions!$B$20)+Assumptions!$B$21*D60+Assumptions!$B$22*MIN(D60,Assumptions!$B$23)+Assumptions!$B$24*MIN(D60,Assumptions!$B$25) -> 7420.7 | F60: =D60+E60 -> 102420.7 | G60: =F60-$F$55 -> 16147.5 | K60: same cost as A2, but variable
A61: C $90,000 + 10% bonus ← recommended | B61: 90000 | C61: 9000 | D61: =B61+C61 -> 99000 | E61: =Assumptions!$B$19*MIN(D61,Assumptions!$B$20)+Assumptions!$B$21*D61+Assumptions!$B$22*MIN(D61,Assumptions!$B$23)+Assumptions!$B$24*MIN(D61,Assumptions!$B$25) -> 7726.7 | F61: =D61+E61 -> 106726.7 | G61: =F61-$F$55 -> 20453.5 | K61: $90k floor, $99k at target; the raise is committed, the rest is earned
A62: Billable share she would need for a $100,000 salary to pay for itself | C62: =IFERROR(107803.2/(('Monthly Capacity'!$N$13-'Monthly Capacity'!$P$27*12-'Monthly Capacity'!$R$27)*'Monthly Capacity'!$T$27*Assumptions!$B$35),0) -> 0.63890865 | K62: at zero margin, against her 15% today — the raise comes out of firm margin, not her own production
A63: Salary and bonus cost the SAME. Her base is already past the FUTA and AZ SUTA wage bases and far below the Social Security cap, so every extra dollar costs 7.65% either way. The choice is about commitment and timing, not money.

Sheet Benefits
A1: Onyx Accounting Group, LLC
A2: Benefits — Health Insurance, 401(k) and PEO Fees
A3: Insperity HR360 proposal, Liberty Saver, 1000 Deductible plan. Prepared 12 Aug 2026, bid expires 25 Sep 2026, anticipated start 25 Oct 2026.
A4: Insperity's own default has the client paying a FLAT $509.76 per employee at every tier. Your $338 / $676 / $1,014 policy is a decision to subsidise DEPENDENT coverage.
A6: 1. EMPLOYEE CONTRIBUTION POLICY
A7: Base employee price — employee only | B7: 338 | H7: Your target. Insperity's own default for this tier is $338.17, so this matches it.
A9: 2. 1000 DEDUCTIBLE PLAN — TIERS
A10: Coverage tier | B10: Total monthly allocation | C10: Employee multiple | D10: Employee pays | E10: Employer pays | F10: Insperity default employer
A11: Employee Only | B11: 847.93 | C11: 1 | D11: =$B$7*C11 -> 338 | E11: =MAX(0,B11-D11) -> 509.93 | F11: 509.76 | H11: Insperity default employee price is $338.17 — your policy matches
A12: Emp. + Spouse | B12: 1779.11 | C12: 2 | D12: =$B$7*C12 -> 676 | E12: =MAX(0,B12-D12) -> 1103.11 | F12: 509.76 | H12: a spouse costs more than any number of children
A13: Emp. + Child | B13: 1609.32 | C13: 2 | D13: =$B$7*C13 -> 676 | E13: =MAX(0,B13-D13) -> 933.32 | F13: 509.76 | H13: ASSUMPTION — your policy did not name the child tiers
A14: Emp. + Children | B14: 1609.32 | C14: 2 | D14: =$B$7*C14 -> 676 | E14: =MAX(0,B14-D14) -> 933.32 | F14: 509.76 | H14: ASSUMPTION — priced the same as one child; Insperity charges the same
A15: Emp. + Family | B15: 2624.24 | C15: 3 | D15: =$B$7*C15 -> 1014 | E15: =MAX(0,B15-D15) -> 1610.24 | F15: 509.76
A17: 3. ELECTIONS BY EMPLOYEE
A18: Employee | B18: Tier # | C18: Employer medical /mo | D18: 401(k) eligible comp | E18: 401(k) match /mo | F18: Run-rate employer /mo | G18: 2026 average /mo (prorated)
A19: ='Staff P&L'!$A$6 -> Steven Nikolov | B19: 5 | C19: =IFERROR(INDEX($E$11:$E$15,B19),0) -> 1610.24 | D19: ='Staff P&L'!$E$6 -> 184500 | E19: =D19/12*$B$30*$B$31 -> 461.25 | F19: =C19+E19 -> 2071.49 | G19: =F19*$B$44/12 -> 345.24833
A20: ='Staff P&L'!$A$7 -> Lisa Danforth | B20: 5 | C20: =IFERROR(INDEX($E$11:$E$15,B20),0) -> 1610.24 | D20: ='Staff P&L'!$E$7 -> 176000 | E20: =D20/12*$B$30*$B$31 -> 440 | F20: =C20+E20 -> 2050.24 | G20: =F20*$B$44/12 -> 341.70667
A21: ='Staff P&L'!$A$8 -> Jessica Bumphus | B21: 2 | C21: =IFERROR(INDEX($E$11:$E$15,B21),0) -> 1103.11 | D21: ='Staff P&L'!$E$8 -> 125280 | E21: =D21/12*$B$30*$B$31 -> 313.2 | F21: =C21+E21 -> 1416.31 | G21: =F21*$B$44/12 -> 236.05167
A22: ='Staff P&L'!$A$9 -> Christine Johnson | B22: 1 | C22: =IFERROR(INDEX($E$11:$E$15,B22),0) -> 509.93 | D22: ='Staff P&L'!$E$9 -> 83520 | E22: =D22/12*$B$30*$B$31 -> 208.8 | F22: =C22+E22 -> 718.73 | G22: =F22*$B$44/12 -> 119.78833
A23: ='Staff P&L'!$A$10 -> Valentina Dikova | C23: 0 | D23: 0 | E23: 0 | F23: =C23+E23 -> 0 | G23: =F23*$B$44/12 -> 0 | H23: Bulgaria contractor — not on US benefits or the PEO
A24: ='Staff P&L'!$A$11 -> Josephine Mack | B24: 1 | C24: =IFERROR(INDEX($E$11:$E$15,B24),0) -> 509.93 | D24: ='Staff P&L'!$E$11 -> 80000 | E24: =D24/12*$B$30*$B$31 -> 200 | F24: =C24+E24 -> 709.93 | G24: =F24*$B$44/12 -> 118.32167
A25: TOTAL | C25: =SUM(C19:C24) -> 5343.45 | D25: =SUM(D19:D24) -> 649300 | E25: =SUM(E19:E24) -> 1623.25 | F25: =SUM(F19:F24) -> 6966.7 | G25: =SUM(G19:G24) -> 1161.1167 | H25: → column F feeds the PEO benefits column on Staff P&L
A26: Tier # key: 1 Employee Only · 2 Emp+Spouse · 3 Emp+Child · 4 Emp+Children · 5 Emp+Family
A27: ⚠ Tiers below are a GUESS that reproduces the proposal's census (2 family, 1 spouse, 2 employee-only). Set each person's real election.
A29: 4. 401(k) MATCH
A30: Employer match — % of eligible comp | B30: 0.03 | H30: You said start at 1–3%. Set it here; the sensitivity below prices each level.
A31: Participation assumption | B31: 1 | H31: Share of eligible employees who contribute enough to earn the full match. 100% is the conservative budget case.
A32: Annual match cost at the setting above | B32: =E25*12 -> 19479
A33: Sensitivity — annual cost at 1% / 2% / 3% | B33: =SUM(D19:D24)*0.01*$B$31 -> 6493 | C33: =SUM(D19:D24)*0.02*$B$31 -> 12986 | D33: =SUM(D19:D24)*0.03*$B$31 -> 19479 | H33: 1% · 2% · 3% of eligible W-2 comp
A35: 5. PEO SERVICE FEES (Insperity HR360)
A36: ⚠ Do NOT add Insperity's 8.00%-of-payroll payroll-tax allocation. The model already computes employer SS, Medicare, FUTA and AZ SUTA on the Assumptions tab, and does it more accurately because it respects each wage base.
A37: HR admin fee — per employee per month | B37: 183 | H37: Proposal: $183.00 per full-time employee per month
A38: Workers' comp & EPLI — % of payroll | B38: 0.0017 | H38: Proposal: 0.17% of gross payroll
A39: PEO payroll-tax load above the model's own — % of payroll | B39: 0.00233 | H39: Insperity allocates 8.00%; the model's own statutory calc is about 7.77%. Only the difference is incremental, so only the difference is charged here.
A40: W-2 employees enrolled | B40: =COUNT(B19:B24) -> 5
A41: US W-2 payroll subject to the fee | B41: =SUM(D19:D24)+'Staff P&L'!$H$25 -> 667005.6 | H41: base comp of W-2 staff plus W-2 bonuses
A42: One-time enrollment fee | B42: 2824.61
A43: First month the PEO is in effect (1 = Jan … 12 = Dec) | B43: 11 | H43: Anticipated start 25 Oct 2026, so November is the first full month — only 2 of 2026.
A44: Months of PEO in 2026 | B44: =MAX(0,13-$B$43) -> 2
A46: 6. EMPLOYER COST SUMMARY
B47: Per month | C47: Annual (12 mo)
A48: Medical — employer share | B48: =C25 -> 5343.45 | C48: =B48*12 -> 64121.4 | H48: from the elections above, under your contribution policy
A49: 401(k) match | B49: =E25 -> 1623.25 | C49: =B49*12 -> 19479
A50: PEO HR admin | B50: =$B$37*$B$40 -> 915 | C50: =B50*12 -> 10980
A51: PEO workers' comp & EPLI | B51: =$B$41/12*$B$38 -> 94.49246 | C51: =B51*12 -> 1133.9095
A52: PEO incremental payroll-tax load | B52: =$B$41/12*$B$39 -> 129.51025 | C52: =B52*12 -> 1554.123 | H52: only the excess over the model's own statutory calculation
A53: TOTAL EMPLOYER BENEFIT + PEO COST | B53: =B48+B49+B50+B51+B52 -> 8105.7027 | C53: =B53*12 -> 97268.433
A54: Per enrolled employee per month | B54: =IFERROR(B53/$B$40,0) -> 1621.1405
A55: 2026 impact — PEO months only, plus the enrolment fee | C55: =B53*$B$44+$B$42 -> 19036.015 | H55: what actually lands in the 2026 P&L given the late-October start
A57: • The proposal is priced on $564,922 of gross payroll. Actual 2026 US W-2 payroll in this model is higher, so Insperity's headline $88,295 service fee will be higher too — the fee scales with payroll. Ask them to re-quote on the real number before signing.
A58: • Medical is the swing item. Insperity's flat $509.76 default costs about $30,600 a year; your contribution policy roughly doubles it, because you absorb the dependent load that their default pushes onto the employee.
A59: • Dental and vision show zero electing and no allocation in the proposal — nothing is budgeted for them here.
A60: • Everything on this tab is an Insperity ALLOCATION, not an insurance premium. Their own disclaimer says so, and COBRA rates can differ materially.

Sheet Monthly Capacity
A1: Onyx Accounting Group, LLC
A2: Monthly Capacity — Working Days → Billable Hours → Revenue
A3: Real 2026 calendar drives the budget. Working days = weekdays − company holidays. Holidays are removed HERE, so never subtract them again downstream. Utilization is now per person, in column T.
B5: Jan 2026 | C5: Feb 2026 | D5: Mar 2026 | E5: Apr 2026 | F5: May 2026 | G5: Jun 2026 | H5: Jul 2026 | I5: Aug 2026 | J5: Sep 2026 | K5: Oct 2026 | L5: Nov 2026 | M5: Dec 2026 | N5: Total / Yr
A7: 1. CALENDAR
A8: Calendar days | B8: 31 | C8: 28 | D8: 31 | E8: 30 | F8: 31 | G8: 30 | H8: 31 | I8: 31 | J8: 30 | K8: 31 | L8: 30 | M8: 31 | N8: =SUM(B8:M8) -> 365
A9: Weekdays (Mon–Fri) | B9: 22 | C9: 20 | D9: 22 | E9: 22 | F9: 21 | G9: 22 | H9: 23 | I9: 21 | J9: 22 | K9: 22 | L9: 21 | M9: 23 | N9: =SUM(B9:M9) -> 261
A10: Company holidays | B10: 1 | C10: 0 | D10: 0 | E10: 0 | F10: 1 | G10: 0 | H10: 1 | I10: 0 | J10: 1 | K10: 0 | L10: 1 | M10: 2 | N10: =SUM(B10:M10) -> 7
A11: Working days | B11: =B9-B10 -> 21 | C11: =C9-C10 -> 20 | D11: =D9-D10 -> 22 | E11: =E9-E10 -> 22 | F11: =F9-F10 -> 20 | G11: =G9-G10 -> 22 | H11: =H9-H10 -> 22 | I11: =I9-I10 -> 21 | ... M11: =M9-M10 -> 21 | N11: =SUM(B11:M11) -> 254
A12: Hours per day | B12: 8 | C12: 8 | D12: 8 | E12: 8 | F12: 8 | G12: 8 | H12: 8 | I12: 8 | J12: 8 | K12: 8 | L12: 8 | M12: 8 | N12: =SUM(B12:M12) -> 96
A13: Gross working hrs / FTE | B13: =B11*B12 -> 168 | C13: =C11*C12 -> 160 | D13: =D11*D12 -> 176 | E13: =E11*E12 -> 176 | F13: =F11*F12 -> 160 | G13: =G11*G12 -> 176 | H13: =H11*H12 -> 176 | I13: =I11*I12 -> 168 | ... M13: =M11*M12 -> 168 | N13: =SUM(B13:M13) -> 2032
A14: Paid hrs / FTE (incl. holidays) | B14: =B9*B12 -> 176 | C14: =C9*C12 -> 160 | D14: =D9*D12 -> 176 | E14: =E9*E12 -> 176 | F14: =F9*F12 -> 168 | G14: =G9*G12 -> 176 | H14: =H9*H12 -> 184 | I14: =I9*I12 -> 168 | ... M14: =M9*M12 -> 184 | N14: =SUM(B14:M14) -> 2088 | P14: ← drives hourly pay & loaded-cost divisor
A16: 2. PTO SHAPING (per-person annual PTO hours are set in block 3)
A17: PTO distribution % of annual | B17: 0.083333333 | C17: 0.083333333 | D17: 0.083333333 | E17: 0.083333333 | F17: 0.083333333 | G17: 0.083333333 | H17: 0.083333333 | I17: 0.083333333 | J17: 0.083333333 | K17: 0.083333333 | L17: 0.083333333 | M17: 0.083333333 | N17: =SUM(B17:M17) -> 1 | P17: must total 100%
A18: Check: PTO distribution totals 100% | B18: =IF(ROUND(N17,6)=1,"OK","FIX — must total 100%") -> OK
A20: 3. BILLABLE HOURS BY PERSON
A21: Employee | B21: Jan | C21: Feb | D21: Mar | E21: Apr | F21: May | G21: Jun | H21: Jul | I21: Aug | J21: Sep | K21: Oct | L21: Nov | M21: Dec | N21: Total hrs | P21: Admin hrs /mo | Q21: Billable share % | R21: Annual PTO hrs | S21: Bill rate $/hr | T21: Utilization %
A22: ='Staff P&L'!$A$6 -> Steven Nikolov | B22: =IF(Assumptions!$B$38=2,B$75,MAX(0,(B$13-$P22-$R22*B$17))*$Q22*$T22) -> 73.406667 | C22: =IF(Assumptions!$B$38=2,C$75,MAX(0,(C$13-$P22-$R22*C$17))*$Q22*$T22) -> 69.766667 | D22: =IF(Assumptions!$B$38=2,D$75,MAX(0,(D$13-$P22-$R22*D$17))*$Q22*$T22) -> 77.046667 | E22: =IF(Assumptions!$B$38=2,E$75,MAX(0,(E$13-$P22-$R22*E$17))*$Q22*$T22) -> 77.046667 | F22: =IF(Assumptions!$B$38=2,F$75,MAX(0,(F$13-$P22-$R22*F$17))*$Q22*$T22) -> 69.766667 | G22: =IF(Assumptions!$B$38=2,G$75,MAX(0,(G$13-$P22-$R22*G$17))*$Q22*$T22) -> 77.046667 | H22: =IF(Assumptions!$B$38=2,H$75,MAX(0,(H$13-$P22-$R22*H$17))*$Q22*$T22) -> 77.046667 | I22: =IF(Assumptions!$B$38=2,I$75,MAX(0,(I$13-$P22-$R22*I$17))*$Q22*$T22) -> 73.406667 | ... M22: =IF(Assumptions!$B$38=2,M$75,MAX(0,(M$13-$P22-$R22*M$17))*$Q22*$T22) -> 73.406667 | N22: =SUM(B22:M22) -> 888.16 | P22: 0 | Q22: 0.5 | R22: 80 | S22: =Assumptions!$B$33 -> 246.57126 | T22: =Assumptions!$B$15 -> 0.91
A23: ='Staff P&L'!$A$7 -> Lisa Danforth | B23: =MAX(0,(B$13-$P23-$R23*B$17))*$Q23*$T23 -> 128.61333 | C23: =MAX(0,(C$13-$P23-$R23*C$17))*$Q23*$T23 -> 121.33333 | D23: =MAX(0,(D$13-$P23-$R23*D$17))*$Q23*$T23 -> 135.89333 | E23: =MAX(0,(E$13-$P23-$R23*E$17))*$Q23*$T23 -> 135.89333 | F23: =MAX(0,(F$13-$P23-$R23*F$17))*$Q23*$T23 -> 121.33333 | G23: =MAX(0,(G$13-$P23-$R23*G$17))*$Q23*$T23 -> 135.89333 | H23: =MAX(0,(H$13-$P23-$R23*H$17))*$Q23*$T23 -> 135.89333 | I23: =MAX(0,(I$13-$P23-$R23*I$17))*$Q23*$T23 -> 128.61333 | ... M23: =MAX(0,(M$13-$P23-$R23*M$17))*$Q23*$T23 -> 128.61333 | N23: =SUM(B23:M23) -> 1557.92 | P23: 20 | Q23: 1 | R23: 80 | S23: =Assumptions!$B$33 -> 246.57126 | T23: =Assumptions!$B$15 -> 0.91
A24: ='Staff P&L'!$A$8 -> Jessica Bumphus | B24: =MAX(0,(B$13-$P24-$R24*B$17))*$Q24*$T24 -> 128.61333 | C24: =MAX(0,(C$13-$P24-$R24*C$17))*$Q24*$T24 -> 121.33333 | D24: =MAX(0,(D$13-$P24-$R24*D$17))*$Q24*$T24 -> 135.89333 | E24: =MAX(0,(E$13-$P24-$R24*E$17))*$Q24*$T24 -> 135.89333 | F24: =MAX(0,(F$13-$P24-$R24*F$17))*$Q24*$T24 -> 121.33333 | G24: =MAX(0,(G$13-$P24-$R24*G$17))*$Q24*$T24 -> 135.89333 | H24: =MAX(0,(H$13-$P24-$R24*H$17))*$Q24*$T24 -> 135.89333 | I24: =MAX(0,(I$13-$P24-$R24*I$17))*$Q24*$T24 -> 128.61333 | ... M24: =MAX(0,(M$13-$P24-$R24*M$17))*$Q24*$T24 -> 128.61333 | N24: =SUM(B24:M24) -> 1557.92 | P24: 20 | Q24: 1 | R24: 80 | S24: =Assumptions!$B$34 -> 151.11296 | T24: =Assumptions!$B$15 -> 0.91
A25: ='Staff P&L'!$A$9 -> Christine Johnson | B25: =MAX(0,(B$13-$P25-$R25*B$17))*$Q25*$T25 -> 128.61333 | C25: =MAX(0,(C$13-$P25-$R25*C$17))*$Q25*$T25 -> 121.33333 | D25: =MAX(0,(D$13-$P25-$R25*D$17))*$Q25*$T25 -> 135.89333 | E25: =MAX(0,(E$13-$P25-$R25*E$17))*$Q25*$T25 -> 135.89333 | F25: =MAX(0,(F$13-$P25-$R25*F$17))*$Q25*$T25 -> 121.33333 | G25: =MAX(0,(G$13-$P25-$R25*G$17))*$Q25*$T25 -> 135.89333 | H25: =MAX(0,(H$13-$P25-$R25*H$17))*$Q25*$T25 -> 135.89333 | I25: =MAX(0,(I$13-$P25-$R25*I$17))*$Q25*$T25 -> 128.61333 | ... M25: =MAX(0,(M$13-$P25-$R25*M$17))*$Q25*$T25 -> 128.61333 | N25: =SUM(B25:M25) -> 1557.92 | P25: 20 | Q25: 1 | R25: 80 | S25: =Assumptions!$B$35 -> 94.988641 | T25: =Assumptions!$B$15 -> 0.91
A26: ='Staff P&L'!$A$10 -> Valentina Dikova | B26: =MAX(0,(B$13-$P26-$R26*B$17))*$Q26*$T26 -> 134.68 | C26: =MAX(0,(C$13-$P26-$R26*C$17))*$Q26*$T26 -> 127.4 | D26: =MAX(0,(D$13-$P26-$R26*D$17))*$Q26*$T26 -> 141.96 | E26: =MAX(0,(E$13-$P26-$R26*E$17))*$Q26*$T26 -> 141.96 | F26: =MAX(0,(F$13-$P26-$R26*F$17))*$Q26*$T26 -> 127.4 | G26: =MAX(0,(G$13-$P26-$R26*G$17))*$Q26*$T26 -> 141.96 | H26: =MAX(0,(H$13-$P26-$R26*H$17))*$Q26*$T26 -> 141.96 | I26: =MAX(0,(I$13-$P26-$R26*I$17))*$Q26*$T26 -> 134.68 | ... M26: =MAX(0,(M$13-$P26-$R26*M$17))*$Q26*$T26 -> 134.68 | N26: =SUM(B26:M26) -> 1630.72 | P26: 20 | Q26: 1 | R26: 0 | S26: =Assumptions!$B$35 -> 94.988641 | T26: =Assumptions!$B$15 -> 0.91
A27: ='Staff P&L'!$A$11 -> Josephine Mack | B27: =MAX(0,(B$13-$P27-$R27*B$17))*$Q27*$T27 -> 22.022 | C27: =MAX(0,(C$13-$P27-$R27*C$17))*$Q27*$T27 -> 20.93 | D27: =MAX(0,(D$13-$P27-$R27*D$17))*$Q27*$T27 -> 23.114 | E27: =MAX(0,(E$13-$P27-$R27*E$17))*$Q27*$T27 -> 23.114 | F27: =MAX(0,(F$13-$P27-$R27*F$17))*$Q27*$T27 -> 20.93 | G27: =MAX(0,(G$13-$P27-$R27*G$17))*$Q27*$T27 -> 23.114 | H27: =MAX(0,(H$13-$P27-$R27*H$17))*$Q27*$T27 -> 23.114 | I27: =MAX(0,(I$13-$P27-$R27*I$17))*$Q27*$T27 -> 22.022 | ... M27: =MAX(0,(M$13-$P27-$R27*M$17))*$Q27*$T27 -> 22.022 | N27: =SUM(B27:M27) -> 266.448 | P27: 0 | Q27: 0.15 | R27: 80 | S27: =Assumptions!$B$35 -> 94.988641 | T27: =Assumptions!$B$15 -> 0.91
A28: Total billable hours | B28: =SUM(B22:B27) -> 615.94867 | C28: =SUM(C22:C27) -> 582.09667 | D28: =SUM(D22:D27) -> 649.80067 | E28: =SUM(E22:E27) -> 649.80067 | F28: =SUM(F22:F27) -> 582.09667 | G28: =SUM(G22:G27) -> 649.80067 | H28: =SUM(H22:H27) -> 649.80067 | I28: =SUM(I22:I27) -> 615.94867 | ... N28: =SUM(N22:N27) -> 7459.088 | P28: weighted avg util → | Q28: =IFERROR(SUMPRODUCT($N$22:$N$27)/SUMPRODUCT(($N$22:$N$27)/$T$22:$T$27),0) -> 0.91
A30: 4. REVENUE BY PERSON (billable hours × bill rate)
A31: ='Staff P&L'!$A$6 -> Steven Nikolov | B31: =B22*$S22 -> 18099.974 | C31: =C22*$S22 -> 17202.455 | D31: =D22*$S22 -> 18997.493 | E31: =E22*$S22 -> 18997.493 | F31: =F22*$S22 -> 17202.455 | G31: =G22*$S22 -> 18997.493 | H31: =H22*$S22 -> 18997.493 | I31: =I22*$S22 -> 18099.974 | ... M31: =M22*$S22 -> 18099.974 | N31: =SUM(B31:M31) -> 218994.73
A32: ='Staff P&L'!$A$7 -> Lisa Danforth | B32: =B23*$S23 -> 31712.351 | C32: =C23*$S23 -> 29917.313 | D32: =D23*$S23 -> 33507.39 | E32: =E23*$S23 -> 33507.39 | F32: =F23*$S23 -> 29917.313 | G32: =G23*$S23 -> 33507.39 | H32: =H23*$S23 -> 33507.39 | I32: =I23*$S23 -> 31712.351 | ... M32: =M23*$S23 -> 31712.351 | N32: =SUM(B32:M32) -> 384138.29
A33: ='Staff P&L'!$A$8 -> Jessica Bumphus | B33: =B24*$S24 -> 19435.141 | C33: =C24*$S24 -> 18335.039 | D33: =D24*$S24 -> 20535.243 | E33: =E24*$S24 -> 20535.243 | F33: =F24*$S24 -> 18335.039 | G33: =G24*$S24 -> 20535.243 | H33: =H24*$S24 -> 20535.243 | I33: =I24*$S24 -> 19435.141 | ... M33: =M24*$S24 -> 19435.141 | N33: =SUM(B33:M33) -> 235421.9
A34: ='Staff P&L'!$A$9 -> Christine Johnson | B34: =B25*$S25 -> 12216.806 | C34: =C25*$S25 -> 11525.288 | D34: =D25*$S25 -> 12908.323 | E34: =E25*$S25 -> 12908.323 | F34: =F25*$S25 -> 11525.288 | G34: =G25*$S25 -> 12908.323 | H34: =H25*$S25 -> 12908.323 | I34: =I25*$S25 -> 12216.806 | ... M34: =M25*$S25 -> 12216.806 | N34: =SUM(B34:M34) -> 147984.7
A35: ='Staff P&L'!$A$10 -> Valentina Dikova | B35: =B26*$S26 -> 12793.07 | C35: =C26*$S26 -> 12101.553 | D35: =D26*$S26 -> 13484.588 | E35: =E26*$S26 -> 13484.588 | F35: =F26*$S26 -> 12101.553 | G35: =G26*$S26 -> 13484.588 | H35: =H26*$S26 -> 13484.588 | I35: =I26*$S26 -> 12793.07 | ... M35: =M26*$S26 -> 12793.07 | N35: =SUM(B35:M35) -> 154899.88
A36: ='Staff P&L'!$A$11 -> Josephine Mack | B36: =B27*$S27 -> 2091.8399 | C36: =C27*$S27 -> 1988.1123 | D36: =D27*$S27 -> 2195.5675 | E36: =E27*$S27 -> 2195.5675 | F36: =F27*$S27 -> 1988.1123 | G36: =G27*$S27 -> 2195.5675 | H36: =H27*$S27 -> 2195.5675 | I36: =I27*$S27 -> 2091.8399 | ... M36: =M27*$S27 -> 2091.8399 | N36: =SUM(B36:M36) -> 25309.534
A37: TOTAL REVENUE → Budget P&L | B37: =SUM(B31:B36) -> 96349.182 | C37: =SUM(C31:C36) -> 91069.76 | D37: =SUM(D31:D36) -> 101628.6 | E37: =SUM(E31:E36) -> 101628.6 | F37: =SUM(F31:F36) -> 91069.76 | G37: =SUM(G31:G36) -> 101628.6 | H37: =SUM(H31:H36) -> 101628.6 | I37: =SUM(I31:I36) -> 96349.182 | ... N37: =SUM(N31:N36) -> 1166749
A39: 5. HOURLY-STAFF WAGE COST (paid hours × pay rate)
A40: ='Staff P&L'!$A$8 -> Jessica Bumphus | B40: =B14*'Staff P&L'!$D$8 -> 10560 | C40: =C14*'Staff P&L'!$D$8 -> 9600 | D40: =D14*'Staff P&L'!$D$8 -> 10560 | E40: =E14*'Staff P&L'!$D$8 -> 10560 | F40: =F14*'Staff P&L'!$D$8 -> 10080 | G40: =G14*'Staff P&L'!$D$8 -> 10560 | H40: =H14*'Staff P&L'!$D$8 -> 11040 | I40: =I14*'Staff P&L'!$D$8 -> 10080 | ... M40: =M14*'Staff P&L'!$D$8 -> 11040 | N40: =SUM(B40:M40) -> 125280 | P40: paid hrs incl. holidays × $/hr
A41: ='Staff P&L'!$A$9 -> Christine Johnson | B41: =B14*'Staff P&L'!$D$9 -> 7040 | C41: =C14*'Staff P&L'!$D$9 -> 6400 | D41: =D14*'Staff P&L'!$D$9 -> 7040 | E41: =E14*'Staff P&L'!$D$9 -> 7040 | F41: =F14*'Staff P&L'!$D$9 -> 6720 | G41: =G14*'Staff P&L'!$D$9 -> 7040 | H41: =H14*'Staff P&L'!$D$9 -> 7360 | I41: =I14*'Staff P&L'!$D$9 -> 6720 | ... M41: =M14*'Staff P&L'!$D$9 -> 7360 | N41: =SUM(B41:M41) -> 83520
A42: Total hourly wages | B42: =SUM(B40:B41) -> 17600 | C42: =SUM(C40:C41) -> 16000 | D42: =SUM(D40:D41) -> 17600 | E42: =SUM(E40:E41) -> 17600 | F42: =SUM(F40:F41) -> 16800 | G42: =SUM(G40:G41) -> 17600 | H42: =SUM(H40:H41) -> 18400 | I42: =SUM(I40:I41) -> 16800 | ... N42: =SUM(N40:N41) -> 208800
A44: • Working days = weekdays − company holidays (7/yr per the Onyx Handbook). Holidays are already excluded here, so the model must NOT deduct them again downstream.
A45: • Billable hours = (gross working hrs − admin hrs − PTO for the month) × billable share × utilization (Assumptions!B15).
A46: • Paid hours include holidays because the handbook pays them; that is the divisor for hourly wages and loaded cost per hour.
A47: • 2026 has 254 working days / 2,032 working hours and 261 weekdays / 2,088 paid hours per FTE.
A50: JULY 2026 OBSERVED (Harvest) — read the definitions before comparing
A51: Total hours logged | C51: 958.7
A52: Billable hours | C52: 630.9
A53: Admin hours (Onyx admin + operations admin) | C53: 214.4
A54: Time off | C54: 113.4
A55: Harvest utilization — billable ÷ ALL hours logged | C55: =IFERROR(C52/C51,0) -> 0.65807865 | E55: NOT comparable with column T — it divides by time off and admin as well
A56: Harvest utilization — billable ÷ hours excluding time off | C56: =IFERROR(C52/(C51-C54),0) -> 0.74636224 | E56: still not the model's definition
A57: Billable-eligible hours in July on the MODEL's definition | C57: =($H$13-$P$22-$R$22*$H$17)*$Q$22+($H$13-$P$23-$R$23*$H$17)*$Q$23+($H$13-$P$24-$R$24*$H$17)*$Q$24+($H$13-$P$25-$R$25*$H$17)*$Q$25+($H$13-$P$26-$R$26*$H$17)*$Q$26+($H$13-$P$27-$R$27*$H$17)*$Q$27 -> 714.06667 | E57: July working hours less admin and PTO, times each person's billable share
A58: UTILIZATION ON THE MODEL'S DEFINITION | C58: =IFERROR(C52/C57,0) -> 0.88353095 | E58: THIS is the number to compare with column T
A59: Plan billable hours for July / actual as % of plan | C59: =$H$28 -> 649.80067 | D59: =IFERROR(C52/C59,0) -> 0.97091313 | E59: hours are close to plan — the gap is in the rate, not the hours
A60: Capacity that reached no timesheet at all | C60: =MAX(0,$H$13*6-C52-C53-C54) -> 97.3 | E60: July calendar capacity for six people, less billable, admin and time off
A61: Note: Harvest gives no role split, so all of this is firm-wide. Pull the Harvest report grouped by person to set column T individually.
A62: Target net income for the year | C62: 400000 | E62: the goal that decides how much Steven has to bill
A63: Total firm cost — all labour fully loaded | C63: ='Staff P&L'!$M$12 -> 783130.93 | E63: every person's pay + employer tax + benefits + bonus. Independent of who bills what.
A64: Non-labour COGS, operating expenses and new-hire cost | C64: =('Budget P&L'!$N$13)+SUM('Budget P&L'!$N$28:$N$39)+'Growth & Hiring'!$N$24 -> 114956.9 | E64: every non-payroll line, plus any hires on the Growth & Hiring tab
A65: PEO service fees — already inside the line above | C65: 0 | E65: kept at zero: HR admin, workers' comp and the tax load are not yet on the P&L, so adding them here would break the calibration. See the PEO line below.
A66: COST BASE | C66: =C63+C64+C65 -> 898087.83
A67: Revenue from everyone except Steven, incl. growth | C67: =SUM($N$32:$N$36)+'Growth & Hiring'!$N$23 -> 1026988.2 | E67: staff capacity and any new clients or hires are consumed first
A68: Revenue Steven must generate | C68: =MAX(0,C62+C66-C67) -> 271099.62
A69: HOURS STEVEN MUST BILL — for the year | C69: =IFERROR(C68/$S$22,0) -> 1099.4778
A70: per month, on average | C70: =C69/12 -> 91.62315
A71: His practical ceiling — working hrs less admin and PTO, at his utilization | C71: =($N$13-$P$22*12-$R$22)*$T$22 -> 1776.32 | E71: 100% of his time billable — the absolute most he could do
A72: Feasible? | C72: =IF(C69<=C71,"YES — "&TEXT(C71-C69,"#,##0")&" hrs of headroom","NO — needs "&TEXT(C69-C71,"#,##0")&" hrs more than he can work") -> YES — 677 hrs of headroom
A73: Implied billable share of his time | C73: =IFERROR(C69/(($N$13-$P$22*12-$R$22)),0) -> 0.56325707 | E73: compare with the 50% in column Q — this is what the target actually demands
A75: Required hours by month | B75: =IFERROR($C$69*MAX(0,(B$13-$P$22-$R$22*B$17))/($N$13-$P$22*12-$R$22),0) -> 90.872141 | C75: =IFERROR($C$69*MAX(0,(C$13-$P$22-$R$22*C$17))/($N$13-$P$22*12-$R$22),0) -> 86.366084 | D75: =IFERROR($C$69*MAX(0,(D$13-$P$22-$R$22*D$17))/($N$13-$P$22*12-$R$22),0) -> 95.378197 | E75: =IFERROR($C$69*MAX(0,(E$13-$P$22-$R$22*E$17))/($N$13-$P$22*12-$R$22),0) -> 95.378197 | F75: =IFERROR($C$69*MAX(0,(F$13-$P$22-$R$22*F$17))/($N$13-$P$22*12-$R$22),0) -> 86.366084 | G75: =IFERROR($C$69*MAX(0,(G$13-$P$22-$R$22*G$17))/($N$13-$P$22*12-$R$22),0) -> 95.378197 | H75: =IFERROR($C$69*MAX(0,(H$13-$P$22-$R$22*H$17))/($N$13-$P$22*12-$R$22),0) -> 95.378197 | I75: =IFERROR($C$69*MAX(0,(I$13-$P$22-$R$22*I$17))/($N$13-$P$22*12-$R$22),0) -> 90.872141 | ... M75: =IFERROR($C$69*MAX(0,(M$13-$P$22-$R$22*M$17))/($N$13-$P$22*12-$R$22),0) -> 90.872141 | N75: =SUM(B75:M75) -> 1099.4778
A76: spread in proportion to the working days in each month
A77: Calibration check — residual at TODAY's net income should equal today's hours
A78: net income at the current plan | C78: ='Budget P&L'!$N$42 -> 347895.1
A79: hours the formula implies at that net income | C79: =IFERROR((C78+C66-C67)/$S$22,0) -> 888.16
A80: Steven's actual hours in the plan | C80: =$N$22 -> 888.16
A81: match? | C81: =IF(ABS(C79-C80)<1,"OK — formula reproduces the plan","CHECK — differs by "&TEXT(C79-C80,"#,##0.0")&" hrs") -> OK — formula reproduces the plan
A82: Extra hours the PEO would cost, once signed | C82: =IFERROR(Benefits!$C$53/$S$22,0) -> 394.48407 | E82: full-year PEO and benefit cost translated into hours Steven must bill to absorb it
A83: • Why a net-income target and not a revenue target: with a revenue target, raising Christine to $40/hr or Josephine to $95k changes nothing about how much Steven must bill, even though net income falls. With a net-income target those decisions immediately show up as extra hours he has to work — which is the question he asked.
A84: • The cost base is deliberately assembled from Staff P&L column M and the non-payroll P&L lines rather than from the Budget P&L subtotals, because those subtotals depend on Steven's COGS allocation. Building it this way keeps the calculation free of any circular reference.
A85: • In residual mode Steven's COGS/operating split follows his computed hours instead of the fixed 50%, so the P&L geography tracks what he actually does. Net income is identical either way — the split only moves cost between gross profit and operating expenses.

Sheet Growth & Hiring
A1: Onyx Accounting Group, LLC
A2: Growth & Hiring — client wins and added staff for the rest of 2026
A3: Everything here is incremental to the base plan. It flows into the Budget P&L, and therefore into the Aug–Dec months of Forecast 2026. The Jan–Jul actuals never move.
B5: Jan 2026 | C5: Feb 2026 | D5: Mar 2026 | E5: Apr 2026 | F5: May 2026 | G5: Jun 2026 | H5: Jul 2026 | I5: Aug 2026 | J5: Sep 2026 | K5: Oct 2026 | L5: Nov 2026 | M5: Dec 2026 | N5: Total
A7: 1. NEW CLIENT REVENUE
A8: New recurring revenue won in the month | B8: 0 | C8: 0 | D8: 0 | E8: 0 | F8: 0 | G8: 0 | H8: 0 | I8: 3000 | J8: 3000 | K8: 3000 | L8: 3000 | M8: 3000 | N8: =SUM(B8:M8) -> 15000 | P8: monthly fee added that month
A9: Cumulative new recurring revenue | B9: =0+B8 -> 0 | C9: =B9+C8 -> 0 | D9: =C9+D8 -> 0 | E9: =D9+E8 -> 0 | F9: =E9+F8 -> 0 | G9: =F9+G8 -> 0 | H9: =G9+H8 -> 0 | I9: =H9+I8 -> 3000 | J9: =I9+J8 -> 6000 | ... M9: =L9+M8 -> 15000 | N9: =SUM(B9:M9) -> 45000 | P9: ← this is the revenue that reaches the P&L
A10: One-off / project revenue | B10: 0 | C10: 0 | D10: 0 | E10: 0 | F10: 0 | G10: 0 | H10: 0 | I10: 0 | J10: 0 | K10: 0 | L10: 0 | M10: 0 | N10: =SUM(B10:M10) -> 0 | P10: clean-ups, implementations — not recurring
A11: TOTAL INCREMENTAL REVENUE | B11: =B9+B10 -> 0 | C11: =C9+C10 -> 0 | D11: =D9+D10 -> 0 | E11: =E9+E10 -> 0 | F11: =F9+F10 -> 0 | G11: =G9+G10 -> 0 | H11: =H9+H10 -> 0 | I11: =I9+I10 -> 3000 | ... N11: =N9+N10 -> 45000
A13: 2. NEW HIRES
A14: Hire (cost by month) | B14: Jan | C14: Feb | D14: Mar | E14: Apr | F14: May | G14: Jun | H14: Jul | I14: Aug | J14: Sep | K14: Oct | L14: Nov | M14: Dec | N14: Total cost | P14: Annual pay | Q14: Start month | R14: Billable share | S14: Utilization | T14: Bill rate $/hr
A15: Staff accountant #1 | B15: =IF(OR($Q15=0,1<$Q15),0,$P15/12*(1+Assumptions!$B$21+Assumptions!$B$19)) -> 0 | C15: =IF(OR($Q15=0,2<$Q15),0,$P15/12*(1+Assumptions!$B$21+Assumptions!$B$19)) -> 0 | D15: =IF(OR($Q15=0,3<$Q15),0,$P15/12*(1+Assumptions!$B$21+Assumptions!$B$19)) -> 0 | E15: =IF(OR($Q15=0,4<$Q15),0,$P15/12*(1+Assumptions!$B$21+Assumptions!$B$19)) -> 0 | F15: =IF(OR($Q15=0,5<$Q15),0,$P15/12*(1+Assumptions!$B$21+Assumptions!$B$19)) -> 0 | G15: =IF(OR($Q15=0,6<$Q15),0,$P15/12*(1+Assumptions!$B$21+Assumptions!$B$19)) -> 0 | H15: =IF(OR($Q15=0,7<$Q15),0,$P15/12*(1+Assumptions!$B$21+Assumptions!$B$19)) -> 0 | I15: =IF(OR($Q15=0,8<$Q15),0,$P15/12*(1+Assumptions!$B$21+Assumptions!$B$19)) -> 0 | J15: =IF(OR($Q15=0,9<$Q15),0,$P15/12*(1+Assumptions!$B$21+Assumptions!$B$19)) -> 0 | K15: =IF(OR($Q15=0,10<$Q15),0,$P15/12*(1+Assumptions!$B$21+Assumptions!$B$19)) -> 7625.2083 | L15: =IF(OR($Q15=0,11<$Q15),0,$P15/12*(1+Assumptions!$B$21+Assumptions!$B$19)) -> 7625.2083 | M15: =IF(OR($Q15=0,12<$Q15),0,$P15/12*(1+Assumptions!$B$21+Assumptions!$B$19)) -> 7625.2083 | N15: =SUM(B15:M15) -> 22875.625 | P15: 85000 | Q15: 10 | R15: 1 | S15: 0.85 | T15: =Assumptions!$B$35 -> 94.988641 | U15: start month 0 = not hired
A16: Staff accountant #2 | B16: =IF(OR($Q16=0,1<$Q16),0,$P16/12*(1+Assumptions!$B$21+Assumptions!$B$19)) -> 0 | C16: =IF(OR($Q16=0,2<$Q16),0,$P16/12*(1+Assumptions!$B$21+Assumptions!$B$19)) -> 0 | D16: =IF(OR($Q16=0,3<$Q16),0,$P16/12*(1+Assumptions!$B$21+Assumptions!$B$19)) -> 0 | E16: =IF(OR($Q16=0,4<$Q16),0,$P16/12*(1+Assumptions!$B$21+Assumptions!$B$19)) -> 0 | F16: =IF(OR($Q16=0,5<$Q16),0,$P16/12*(1+Assumptions!$B$21+Assumptions!$B$19)) -> 0 | G16: =IF(OR($Q16=0,6<$Q16),0,$P16/12*(1+Assumptions!$B$21+Assumptions!$B$19)) -> 0 | H16: =IF(OR($Q16=0,7<$Q16),0,$P16/12*(1+Assumptions!$B$21+Assumptions!$B$19)) -> 0 | I16: =IF(OR($Q16=0,8<$Q16),0,$P16/12*(1+Assumptions!$B$21+Assumptions!$B$19)) -> 0 | J16: =IF(OR($Q16=0,9<$Q16),0,$P16/12*(1+Assumptions!$B$21+Assumptions!$B$19)) -> 0 | K16: =IF(OR($Q16=0,10<$Q16),0,$P16/12*(1+Assumptions!$B$21+Assumptions!$B$19)) -> 0 | L16: =IF(OR($Q16=0,11<$Q16),0,$P16/12*(1+Assumptions!$B$21+Assumptions!$B$19)) -> 0 | M16: =IF(OR($Q16=0,12<$Q16),0,$P16/12*(1+Assumptions!$B$21+Assumptions!$B$19)) -> 0 | N16: =SUM(B16:M16) -> 0 | P16: 85000 | Q16: 0 | R16: 1 | S16: 0.85 | T16: =Assumptions!$B$35 -> 94.988641 | U16: start month 0 = not hired
A17: Controller #2 | B17: =IF(OR($Q17=0,1<$Q17),0,$P17/12*(1+Assumptions!$B$21+Assumptions!$B$19)) -> 0 | C17: =IF(OR($Q17=0,2<$Q17),0,$P17/12*(1+Assumptions!$B$21+Assumptions!$B$19)) -> 0 | D17: =IF(OR($Q17=0,3<$Q17),0,$P17/12*(1+Assumptions!$B$21+Assumptions!$B$19)) -> 0 | E17: =IF(OR($Q17=0,4<$Q17),0,$P17/12*(1+Assumptions!$B$21+Assumptions!$B$19)) -> 0 | F17: =IF(OR($Q17=0,5<$Q17),0,$P17/12*(1+Assumptions!$B$21+Assumptions!$B$19)) -> 0 | G17: =IF(OR($Q17=0,6<$Q17),0,$P17/12*(1+Assumptions!$B$21+Assumptions!$B$19)) -> 0 | H17: =IF(OR($Q17=0,7<$Q17),0,$P17/12*(1+Assumptions!$B$21+Assumptions!$B$19)) -> 0 | I17: =IF(OR($Q17=0,8<$Q17),0,$P17/12*(1+Assumptions!$B$21+Assumptions!$B$19)) -> 0 | J17: =IF(OR($Q17=0,9<$Q17),0,$P17/12*(1+Assumptions!$B$21+Assumptions!$B$19)) -> 0 | K17: =IF(OR($Q17=0,10<$Q17),0,$P17/12*(1+Assumptions!$B$21+Assumptions!$B$19)) -> 0 | L17: =IF(OR($Q17=0,11<$Q17),0,$P17/12*(1+Assumptions!$B$21+Assumptions!$B$19)) -> 0 | M17: =IF(OR($Q17=0,12<$Q17),0,$P17/12*(1+Assumptions!$B$21+Assumptions!$B$19)) -> 0 | N17: =SUM(B17:M17) -> 0 | P17: 125000 | Q17: 0 | R17: 1 | S17: 0.85 | T17: =Assumptions!$B$34 -> 151.11296 | U17: start month 0 = not hired
A18: Total new-hire cost | B18: =SUM(B15:B17) -> 0 | C18: =SUM(C15:C17) -> 0 | D18: =SUM(D15:D17) -> 0 | E18: =SUM(E15:E17) -> 0 | F18: =SUM(F15:F17) -> 0 | G18: =SUM(G15:G17) -> 0 | H18: =SUM(H15:H17) -> 0 | I18: =SUM(I15:I17) -> 0 | ... N18: =SUM(N15:N17) -> 22875.625
A19: New-hire billable hours | B19: =IF(OR($Q15=0,1<$Q15),0,MAX(0,('Monthly Capacity'!B$13-20-80*'Monthly Capacity'!B$17))*$R15*$S15)+IF(OR($Q16=0,1<$Q16),0,MAX(0,('Monthly Capacity'!B$13-20-80*'Monthly Capacity'!B$17))*$R16*$S16)+IF(OR($Q17=0,1<$Q17),0,MAX(0,('Monthly Capacity'!B$13-20-80*'Monthly Capacity'!B$17))*$R17*$S17) -> 0 | C19: =IF(OR($Q15=0,2<$Q15),0,MAX(0,('Monthly Capacity'!C$13-20-80*'Monthly Capacity'!C$17))*$R15*$S15)+IF(OR($Q16=0,2<$Q16),0,MAX(0,('Monthly Capacity'!C$13-20-80*'Monthly Capacity'!C$17))*$R16*$S16)+IF(OR($Q17=0,2<$Q17),0,MAX(0,('Monthly Capacity'!C$13-20-80*'Monthly Capacity'!C$17))*$R17*$S17) -> 0 | D19: =IF(OR($Q15=0,3<$Q15),0,MAX(0,('Monthly Capacity'!D$13-20-80*'Monthly Capacity'!D$17))*$R15*$S15)+IF(OR($Q16=0,3<$Q16),0,MAX(0,('Monthly Capacity'!D$13-20-80*'Monthly Capacity'!D$17))*$R16*$S16)+IF(OR($Q17=0,3<$Q17),0,MAX(0,('Monthly Capacity'!D$13-20-80*'Monthly Capacity'!D$17))*$R17*$S17) -> 0 | E19: =IF(OR($Q15=0,4<$Q15),0,MAX(0,('Monthly Capacity'!E$13-20-80*'Monthly Capacity'!E$17))*$R15*$S15)+IF(OR($Q16=0,4<$Q16),0,MAX(0,('Monthly Capacity'!E$13-20-80*'Monthly Capacity'!E$17))*$R16*$S16)+IF(OR($Q17=0,4<$Q17),0,MAX(0,('Monthly Capacity'!E$13-20-80*'Monthly Capacity'!E$17))*$R17*$S17) -> 0 | F19: =IF(OR($Q15=0,5<$Q15),0,MAX(0,('Monthly Capacity'!F$13-20-80*'Monthly Capacity'!F$17))*$R15*$S15)+IF(OR($Q16=0,5<$Q16),0,MAX(0,('Monthly Capacity'!F$13-20-80*'Monthly Capacity'!F$17))*$R16*$S16)+IF(OR($Q17=0,5<$Q17),0,MAX(0,('Monthly Capacity'!F$13-20-80*'Monthly Capacity'!F$17))*$R17*$S17) -> 0 | G19: =IF(OR($Q15=0,6<$Q15),0,MAX(0,('Monthly Capacity'!G$13-20-80*'Monthly Capacity'!G$17))*$R15*$S15)+IF(OR($Q16=0,6<$Q16),0,MAX(0,('Monthly Capacity'!G$13-20-80*'Monthly Capacity'!G$17))*$R16*$S16)+IF(OR($Q17=0,6<$Q17),0,MAX(0,('Monthly Capacity'!G$13-20-80*'Monthly Capacity'!G$17))*$R17*$S17) -> 0 | H19: =IF(OR($Q15=0,7<$Q15),0,MAX(0,('Monthly Capacity'!H$13-20-80*'Monthly Capacity'!H$17))*$R15*$S15)+IF(OR($Q16=0,7<$Q16),0,MAX(0,('Monthly Capacity'!H$13-20-80*'Monthly Capacity'!H$17))*$R16*$S16)+IF(OR($Q17=0,7<$Q17),0,MAX(0,('Monthly Capacity'!H$13-20-80*'Monthly Capacity'!H$17))*$R17*$S17) -> 0 | I19: =IF(OR($Q15=0,8<$Q15),0,MAX(0,('Monthly Capacity'!I$13-20-80*'Monthly Capacity'!I$17))*$R15*$S15)+IF(OR($Q16=0,8<$Q16),0,MAX(0,('Monthly Capacity'!I$13-20-80*'Monthly Capacity'!I$17))*$R16*$S16)+IF(OR($Q17=0,8<$Q17),0,MAX(0,('Monthly Capacity'!I$13-20-80*'Monthly Capacity'!I$17))*$R17*$S17) -> 0 | J19: =IF(OR($Q15=0,9<$Q15),0,MAX(0,('Monthly Capacity'!J$13-20-80*'Monthly Capacity'!J$17))*$R15*$S15)+IF(OR($Q16=0,9<$Q16),0,MAX(0,('Monthly Capacity'!J$13-20-80*'Monthly Capacity'!J$17))*$R16*$S16)+IF(OR($Q17=0,9<$Q17),0,MAX(0,('Monthly Capacity'!J$13-20-80*'Monthly Capacity'!J$17))*$R17*$S17) -> 0 | K19: =IF(OR($Q15=0,10<$Q15),0,MAX(0,('Monthly Capacity'!K$13-20-80*'Monthly Capacity'!K$17))*$R15*$S15)+IF(OR($Q16=0,10<$Q16),0,MAX(0,('Monthly Capacity'!K$13-20-80*'Monthly Capacity'!K$17))*$R16*$S16)+IF(OR($Q17=0,10<$Q17),0,MAX(0,('Monthly Capacity'!K$13-20-80*'Monthly Capacity'!K$17))*$R17*$S17) -> 126.93333 | L19: =IF(OR($Q15=0,11<$Q15),0,MAX(0,('Monthly Capacity'!L$13-20-80*'Monthly Capacity'!L$17))*$R15*$S15)+IF(OR($Q16=0,11<$Q16),0,MAX(0,('Monthly Capacity'!L$13-20-80*'Monthly Capacity'!L$17))*$R16*$S16)+IF(OR($Q17=0,11<$Q17),0,MAX(0,('Monthly Capacity'!L$13-20-80*'Monthly Capacity'!L$17))*$R17*$S17) -> 113.33333 | M19: =IF(OR($Q15=0,12<$Q15),0,MAX(0,('Monthly Capacity'!M$13-20-80*'Monthly Capacity'!M$17))*$R15*$S15)+IF(OR($Q16=0,12<$Q16),0,MAX(0,('Monthly Capacity'!M$13-20-80*'Monthly Capacity'!M$17))*$R16*$S16)+IF(OR($Q17=0,12<$Q17),0,MAX(0,('Monthly Capacity'!M$13-20-80*'Monthly Capacity'!M$17))*$R17*$S17) -> 120.13333 | N19: =SUM(B19:M19) -> 360.4
A20: New-hire revenue | B20: =IF(OR($Q15=0,1<$Q15),0,MAX(0,('Monthly Capacity'!B$13-20-80*'Monthly Capacity'!B$17))*$R15*$S15*$T15)+IF(OR($Q16=0,1<$Q16),0,MAX(0,('Monthly Capacity'!B$13-20-80*'Monthly Capacity'!B$17))*$R16*$S16*$T16)+IF(OR($Q17=0,1<$Q17),0,MAX(0,('Monthly Capacity'!B$13-20-80*'Monthly Capacity'!B$17))*$R17*$S17*$T17) -> 0 | C20: =IF(OR($Q15=0,2<$Q15),0,MAX(0,('Monthly Capacity'!C$13-20-80*'Monthly Capacity'!C$17))*$R15*$S15*$T15)+IF(OR($Q16=0,2<$Q16),0,MAX(0,('Monthly Capacity'!C$13-20-80*'Monthly Capacity'!C$17))*$R16*$S16*$T16)+IF(OR($Q17=0,2<$Q17),0,MAX(0,('Monthly Capacity'!C$13-20-80*'Monthly Capacity'!C$17))*$R17*$S17*$T17) -> 0 | D20: =IF(OR($Q15=0,3<$Q15),0,MAX(0,('Monthly Capacity'!D$13-20-80*'Monthly Capacity'!D$17))*$R15*$S15*$T15)+IF(OR($Q16=0,3<$Q16),0,MAX(0,('Monthly Capacity'!D$13-20-80*'Monthly Capacity'!D$17))*$R16*$S16*$T16)+IF(OR($Q17=0,3<$Q17),0,MAX(0,('Monthly Capacity'!D$13-20-80*'Monthly Capacity'!D$17))*$R17*$S17*$T17) -> 0 | E20: =IF(OR($Q15=0,4<$Q15),0,MAX(0,('Monthly Capacity'!E$13-20-80*'Monthly Capacity'!E$17))*$R15*$S15*$T15)+IF(OR($Q16=0,4<$Q16),0,MAX(0,('Monthly Capacity'!E$13-20-80*'Monthly Capacity'!E$17))*$R16*$S16*$T16)+IF(OR($Q17=0,4<$Q17),0,MAX(0,('Monthly Capacity'!E$13-20-80*'Monthly Capacity'!E$17))*$R17*$S17*$T17) -> 0 | F20: =IF(OR($Q15=0,5<$Q15),0,MAX(0,('Monthly Capacity'!F$13-20-80*'Monthly Capacity'!F$17))*$R15*$S15*$T15)+IF(OR($Q16=0,5<$Q16),0,MAX(0,('Monthly Capacity'!F$13-20-80*'Monthly Capacity'!F$17))*$R16*$S16*$T16)+IF(OR($Q17=0,5<$Q17),0,MAX(0,('Monthly Capacity'!F$13-20-80*'Monthly Capacity'!F$17))*$R17*$S17*$T17) -> 0 | G20: =IF(OR($Q15=0,6<$Q15),0,MAX(0,('Monthly Capacity'!G$13-20-80*'Monthly Capacity'!G$17))*$R15*$S15*$T15)+IF(OR($Q16=0,6<$Q16),0,MAX(0,('Monthly Capacity'!G$13-20-80*'Monthly Capacity'!G$17))*$R16*$S16*$T16)+IF(OR($Q17=0,6<$Q17),0,MAX(0,('Monthly Capacity'!G$13-20-80*'Monthly Capacity'!G$17))*$R17*$S17*$T17) -> 0 | H20: =IF(OR($Q15=0,7<$Q15),0,MAX(0,('Monthly Capacity'!H$13-20-80*'Monthly Capacity'!H$17))*$R15*$S15*$T15)+IF(OR($Q16=0,7<$Q16),0,MAX(0,('Monthly Capacity'!H$13-20-80*'Monthly Capacity'!H$17))*$R16*$S16*$T16)+IF(OR($Q17=0,7<$Q17),0,MAX(0,('Monthly Capacity'!H$13-20-80*'Monthly Capacity'!H$17))*$R17*$S17*$T17) -> 0 | I20: =IF(OR($Q15=0,8<$Q15),0,MAX(0,('Monthly Capacity'!I$13-20-80*'Monthly Capacity'!I$17))*$R15*$S15*$T15)+IF(OR($Q16=0,8<$Q16),0,MAX(0,('Monthly Capacity'!I$13-20-80*'Monthly Capacity'!I$17))*$R16*$S16*$T16)+IF(OR($Q17=0,8<$Q17),0,MAX(0,('Monthly Capacity'!I$13-20-80*'Monthly Capacity'!I$17))*$R17*$S17*$T17) -> 0 | J20: =IF(OR($Q15=0,9<$Q15),0,MAX(0,('Monthly Capacity'!J$13-20-80*'Monthly Capacity'!J$17))*$R15*$S15*$T15)+IF(OR($Q16=0,9<$Q16),0,MAX(0,('Monthly Capacity'!J$13-20-80*'Monthly Capacity'!J$17))*$R16*$S16*$T16)+IF(OR($Q17=0,9<$Q17),0,MAX(0,('Monthly Capacity'!J$13-20-80*'Monthly Capacity'!J$17))*$R17*$S17*$T17) -> 0 | K20: =IF(OR($Q15=0,10<$Q15),0,MAX(0,('Monthly Capacity'!K$13-20-80*'Monthly Capacity'!K$17))*$R15*$S15*$T15)+IF(OR($Q16=0,10<$Q16),0,MAX(0,('Monthly Capacity'!K$13-20-80*'Monthly Capacity'!K$17))*$R16*$S16*$T16)+IF(OR($Q17=0,10<$Q17),0,MAX(0,('Monthly Capacity'!K$13-20-80*'Monthly Capacity'!K$17))*$R17*$S17*$T17) -> 12057.225 | L20: =IF(OR($Q15=0,11<$Q15),0,MAX(0,('Monthly Capacity'!L$13-20-80*'Monthly Capacity'!L$17))*$R15*$S15*$T15)+IF(OR($Q16=0,11<$Q16),0,MAX(0,('Monthly Capacity'!L$13-20-80*'Monthly Capacity'!L$17))*$R16*$S16*$T16)+IF(OR($Q17=0,11<$Q17),0,MAX(0,('Monthly Capacity'!L$13-20-80*'Monthly Capacity'!L$17))*$R17*$S17*$T17) -> 10765.379 | M20: =IF(OR($Q15=0,12<$Q15),0,MAX(0,('Monthly Capacity'!M$13-20-80*'Monthly Capacity'!M$17))*$R15*$S15*$T15)+IF(OR($Q16=0,12<$Q16),0,MAX(0,('Monthly Capacity'!M$13-20-80*'Monthly Capacity'!M$17))*$R16*$S16*$T16)+IF(OR($Q17=0,12<$Q17),0,MAX(0,('Monthly Capacity'!M$13-20-80*'Monthly Capacity'!M$17))*$R17*$S17*$T17) -> 11411.302 | N20: =SUM(B20:M20) -> 34233.906
A22: 3. NET IMPACT
A23: Incremental revenue — clients + new hires | B23: =B11+B20 -> 0 | C23: =C11+C20 -> 0 | D23: =D11+D20 -> 0 | E23: =E11+E20 -> 0 | F23: =F11+F20 -> 0 | G23: =G11+G20 -> 0 | H23: =H11+H20 -> 0 | I23: =I11+I20 -> 3000 | ... N23: =N11+N20 -> 79233.906
A24: Incremental cost — new hires | B24: =B18 -> 0 | C24: =C18 -> 0 | D24: =D18 -> 0 | E24: =E18 -> 0 | F24: =F18 -> 0 | G24: =G18 -> 0 | H24: =H18 -> 0 | I24: =I18 -> 0 | ... N24: =N18 -> 22875.625
A25: NET IMPACT ON NET INCOME | B25: =B23-B24 -> 0 | C25: =C23-C24 -> 0 | D25: =D23-D24 -> 0 | E25: =E23-E24 -> 0 | F25: =F23-F24 -> 0 | G25: =G23-G24 -> 0 | H25: =H23-H24 -> 0 | I25: =I23-I24 -> 3000 | ... N25: =N23-N24 -> 56358.281
A27: • New client revenue is entered as the monthly fee won in that month, then carried forward — a $3,000 client won in August bills $3,000 every month from August on.
A28: • A new hire's capacity uses the same calendar as everyone else: that month's working hours less 20 admin hours and their share of 80 hours PTO, times their billable share and utilization. New hires are assumed to ramp at 85%, not 91%.
A29: • Only the recurring and one-off revenue lines and the hire costs are inputs. Everything else is calculated, and the whole block adds to the Budget P&L, so Forecast 2026 picks it up in August through December.
A30: • New hires here do NOT carry benefits or PEO fees. Add them on the Benefits tab once a hire is real.

Sheet Budget P&L
A1: Onyx Accounting Group, LLC
A2: Budget — Profit and Loss (QuickBooks format)
A3: January–December 2026 (Forecast)
A4: Revenue and hourly wages follow the real 2026 working-day calendar (Monthly Capacity tab). Green = linked; blue = input.
B6: Jan 2026 | C6: Feb 2026 | D6: Mar 2026 | E6: Apr 2026 | F6: May 2026 | G6: Jun 2026 | H6: Jul 2026 | I6: Aug 2026 | J6: Sep 2026 | K6: Oct 2026 | L6: Nov 2026 | M6: Dec 2026 | N6: Total
A7: Income
A8: Billable Expense Income | B8: 0 | C8: 0 | D8: 0 | E8: 0 | F8: 0 | G8: 0 | H8: 0 | I8: 0 | J8: 0 | K8: 0 | L8: 0 | M8: 0 | N8: =SUM(B8:M8) -> 0 | P8: Reimbursed client expenses — input
A9: Sales | B9: ='Monthly Capacity'!B$37+'Growth & Hiring'!B$23 -> 96349.182 | C9: ='Monthly Capacity'!C$37+'Growth & Hiring'!C$23 -> 91069.76 | D9: ='Monthly Capacity'!D$37+'Growth & Hiring'!D$23 -> 101628.6 | E9: ='Monthly Capacity'!E$37+'Growth & Hiring'!E$23 -> 101628.6 | F9: ='Monthly Capacity'!F$37+'Growth & Hiring'!F$23 -> 91069.76 | G9: ='Monthly Capacity'!G$37+'Growth & Hiring'!G$23 -> 101628.6 | H9: ='Monthly Capacity'!H$37+'Growth & Hiring'!H$23 -> 101628.6 | I9: ='Monthly Capacity'!I$37+'Growth & Hiring'!I$23 -> 99349.182 | ... M9: ='Monthly Capacity'!M$37+'Growth & Hiring'!M$23 -> 122760.48 | N9: =SUM(B9:M9) -> 1245982.9 | P9: Σ billable revenue, all staff (Staff P&L)
A10: Total for Income | B10: =B8+B9 -> 96349.182 | C10: =C8+C9 -> 91069.76 | D10: =D8+D9 -> 101628.6 | E10: =E8+E9 -> 101628.6 | F10: =F8+F9 -> 91069.76 | G10: =G8+G9 -> 101628.6 | H10: =H8+H9 -> 101628.6 | I10: =I8+I9 -> 99349.182 | ... N10: =N8+N9 -> 1245982.9
A11: Cost of Goods Sold
A12: Cost of labor - Contractors | B12: ='Staff P&L'!$U$10 -> 4200 | C12: ='Staff P&L'!$U$10 -> 4200 | D12: ='Staff P&L'!$U$10 -> 4200 | E12: ='Staff P&L'!$U$10 -> 4200 | F12: ='Staff P&L'!$U$10 -> 4200 | G12: ='Staff P&L'!$U$10 -> 4200 | H12: ='Staff P&L'!$U$10 -> 4200 | I12: ='Staff P&L'!$U$10 -> 4200 | ... M12: ='Staff P&L'!$U$10 -> 4200 | N12: =SUM(B12:M12) -> 50400 | P12: Valentina (Bulgaria all-in)
A13: Filing Fees | B13: 28.48 | C13: 28.48 | D13: 28.48 | E13: 28.48 | F13: 28.48 | G13: 28.48 | H13: 28.48 | I13: 28.48 | J13: 28.48 | K13: 28.48 | L13: 28.48 | M13: 28.48 | N13: =SUM(B13:M13) -> 341.76 | P13: H1-26 avg ≈ $28/mo
A14: Payroll Expenses
A15: Discretionary Bonuses | B15: 0 | C15: 0 | D15: ='Staff P&L'!$D$25 -> 0 | E15: 0 | F15: 0 | G15: ='Staff P&L'!$E$25 -> 0 | H15: 0 | I15: 0 | J15: ='Staff P&L'!$F$25 -> 8852.8 | K15: 0 | L15: 0 | M15: ='Staff P&L'!$G$25 -> 8852.8 | N15: =SUM(B15:M15) -> 17705.6 | P15: Input
A16: Holiday Pay | B16: 0 | C16: 0 | D16: 0 | E16: 0 | F16: 0 | G16: 0 | H16: 0 | I16: 0 | J16: 0 | K16: 0 | L16: 0 | M16: 0 | N16: =SUM(B16:M16) -> 0 | P16: 0 — embedded in annual wages
A17: Wages | B17: ='Staff P&L'!$E$6/12*'Staff P&L'!$T$6+'Staff P&L'!$E$7/12*'Staff P&L'!$T$7+'Monthly Capacity'!B$40*'Staff P&L'!$T$8+'Monthly Capacity'!B$41*'Staff P&L'!$T$9+'Staff P&L'!$E$11/12*'Staff P&L'!$T$11+'Growth & Hiring'!B$24 -> 40954.167 | C17: ='Staff P&L'!$E$6/12*'Staff P&L'!$T$6+'Staff P&L'!$E$7/12*'Staff P&L'!$T$7+'Monthly Capacity'!C$40*'Staff P&L'!$T$8+'Monthly Capacity'!C$41*'Staff P&L'!$T$9+'Staff P&L'!$E$11/12*'Staff P&L'!$T$11+'Growth & Hiring'!C$24 -> 39354.167 | D17: ='Staff P&L'!$E$6/12*'Staff P&L'!$T$6+'Staff P&L'!$E$7/12*'Staff P&L'!$T$7+'Monthly Capacity'!D$40*'Staff P&L'!$T$8+'Monthly Capacity'!D$41*'Staff P&L'!$T$9+'Staff P&L'!$E$11/12*'Staff P&L'!$T$11+'Growth & Hiring'!D$24 -> 40954.167 | E17: ='Staff P&L'!$E$6/12*'Staff P&L'!$T$6+'Staff P&L'!$E$7/12*'Staff P&L'!$T$7+'Monthly Capacity'!E$40*'Staff P&L'!$T$8+'Monthly Capacity'!E$41*'Staff P&L'!$T$9+'Staff P&L'!$E$11/12*'Staff P&L'!$T$11+'Growth & Hiring'!E$24 -> 40954.167 | F17: ='Staff P&L'!$E$6/12*'Staff P&L'!$T$6+'Staff P&L'!$E$7/12*'Staff P&L'!$T$7+'Monthly Capacity'!F$40*'Staff P&L'!$T$8+'Monthly Capacity'!F$41*'Staff P&L'!$T$9+'Staff P&L'!$E$11/12*'Staff P&L'!$T$11+'Growth & Hiring'!F$24 -> 40154.167 | G17: ='Staff P&L'!$E$6/12*'Staff P&L'!$T$6+'Staff P&L'!$E$7/12*'Staff P&L'!$T$7+'Monthly Capacity'!G$40*'Staff P&L'!$T$8+'Monthly Capacity'!G$41*'Staff P&L'!$T$9+'Staff P&L'!$E$11/12*'Staff P&L'!$T$11+'Growth & Hiring'!G$24 -> 40954.167 | H17: ='Staff P&L'!$E$6/12*'Staff P&L'!$T$6+'Staff P&L'!$E$7/12*'Staff P&L'!$T$7+'Monthly Capacity'!H$40*'Staff P&L'!$T$8+'Monthly Capacity'!H$41*'Staff P&L'!$T$9+'Staff P&L'!$E$11/12*'Staff P&L'!$T$11+'Growth & Hiring'!H$24 -> 41754.167 | I17: ='Staff P&L'!$E$6/12*'Staff P&L'!$T$6+'Staff P&L'!$E$7/12*'Staff P&L'!$T$7+'Monthly Capacity'!I$40*'Staff P&L'!$T$8+'Monthly Capacity'!I$41*'Staff P&L'!$T$9+'Staff P&L'!$E$11/12*'Staff P&L'!$T$11+'Growth & Hiring'!I$24 -> 40154.167 | ... M17: ='Staff P&L'!$E$6/12*'Staff P&L'!$T$6+'Staff P&L'!$E$7/12*'Staff P&L'!$T$7+'Monthly Capacity'!M$40*'Staff P&L'!$T$8+'Monthly Capacity'!M$41*'Staff P&L'!$T$9+'Staff P&L'!$E$11/12*'Staff P&L'!$T$11+'Growth & Hiring'!M$24 -> 49379.375 | N17: =SUM(B17:M17) -> 511925.62 | P17: Production staff, COGS-allocated
A18: Payroll Taxes | B18: ='Staff P&L'!$J$6/12*'Staff P&L'!$T$6+'Staff P&L'!$J$7/12*'Staff P&L'!$T$7+'Staff P&L'!$J$8/12*'Staff P&L'!$T$8+'Staff P&L'!$J$9/12*'Staff P&L'!$T$9+'Staff P&L'!$J$11/12*'Staff P&L'!$T$11 -> 3164.2921 | C18: ='Staff P&L'!$J$6/12*'Staff P&L'!$T$6+'Staff P&L'!$J$7/12*'Staff P&L'!$T$7+'Staff P&L'!$J$8/12*'Staff P&L'!$T$8+'Staff P&L'!$J$9/12*'Staff P&L'!$T$9+'Staff P&L'!$J$11/12*'Staff P&L'!$T$11 -> 3164.2921 | D18: ='Staff P&L'!$J$6/12*'Staff P&L'!$T$6+'Staff P&L'!$J$7/12*'Staff P&L'!$T$7+'Staff P&L'!$J$8/12*'Staff P&L'!$T$8+'Staff P&L'!$J$9/12*'Staff P&L'!$T$9+'Staff P&L'!$J$11/12*'Staff P&L'!$T$11+IFERROR('Staff P&L'!$D$25/'Staff P&L'!$H$25*'Staff P&L'!$I$25,0) -> 3164.2921 | E18: ='Staff P&L'!$J$6/12*'Staff P&L'!$T$6+'Staff P&L'!$J$7/12*'Staff P&L'!$T$7+'Staff P&L'!$J$8/12*'Staff P&L'!$T$8+'Staff P&L'!$J$9/12*'Staff P&L'!$T$9+'Staff P&L'!$J$11/12*'Staff P&L'!$T$11 -> 3164.2921 | F18: ='Staff P&L'!$J$6/12*'Staff P&L'!$T$6+'Staff P&L'!$J$7/12*'Staff P&L'!$T$7+'Staff P&L'!$J$8/12*'Staff P&L'!$T$8+'Staff P&L'!$J$9/12*'Staff P&L'!$T$9+'Staff P&L'!$J$11/12*'Staff P&L'!$T$11 -> 3164.2921 | G18: ='Staff P&L'!$J$6/12*'Staff P&L'!$T$6+'Staff P&L'!$J$7/12*'Staff P&L'!$T$7+'Staff P&L'!$J$8/12*'Staff P&L'!$T$8+'Staff P&L'!$J$9/12*'Staff P&L'!$T$9+'Staff P&L'!$J$11/12*'Staff P&L'!$T$11+IFERROR('Staff P&L'!$E$25/'Staff P&L'!$H$25*'Staff P&L'!$I$25,0) -> 3164.2921 | H18: ='Staff P&L'!$J$6/12*'Staff P&L'!$T$6+'Staff P&L'!$J$7/12*'Staff P&L'!$T$7+'Staff P&L'!$J$8/12*'Staff P&L'!$T$8+'Staff P&L'!$J$9/12*'Staff P&L'!$T$9+'Staff P&L'!$J$11/12*'Staff P&L'!$T$11 -> 3164.2921 | I18: ='Staff P&L'!$J$6/12*'Staff P&L'!$T$6+'Staff P&L'!$J$7/12*'Staff P&L'!$T$7+'Staff P&L'!$J$8/12*'Staff P&L'!$T$8+'Staff P&L'!$J$9/12*'Staff P&L'!$T$9+'Staff P&L'!$J$11/12*'Staff P&L'!$T$11 -> 3164.2921 | J18: ='Staff P&L'!$J$6/12*'Staff P&L'!$T$6+'Staff P&L'!$J$7/12*'Staff P&L'!$T$7+'Staff P&L'!$J$8/12*'Staff P&L'!$T$8+'Staff P&L'!$J$9/12*'Staff P&L'!$T$9+'Staff P&L'!$J$11/12*'Staff P&L'!$T$11+IFERROR('Staff P&L'!$F$25/'Staff P&L'!$H$25*'Staff P&L'!$I$25,0) -> 3841.5313 | K18: ='Staff P&L'!$J$6/12*'Staff P&L'!$T$6+'Staff P&L'!$J$7/12*'Staff P&L'!$T$7+'Staff P&L'!$J$8/12*'Staff P&L'!$T$8+'Staff P&L'!$J$9/12*'Staff P&L'!$T$9+'Staff P&L'!$J$11/12*'Staff P&L'!$T$11 -> 3164.2921 | L18: ='Staff P&L'!$J$6/12*'Staff P&L'!$T$6+'Staff P&L'!$J$7/12*'Staff P&L'!$T$7+'Staff P&L'!$J$8/12*'Staff P&L'!$T$8+'Staff P&L'!$J$9/12*'Staff P&L'!$T$9+'Staff P&L'!$J$11/12*'Staff P&L'!$T$11 -> 3164.2921 | M18: ='Staff P&L'!$J$6/12*'Staff P&L'!$T$6+'Staff P&L'!$J$7/12*'Staff P&L'!$T$7+'Staff P&L'!$J$8/12*'Staff P&L'!$T$8+'Staff P&L'!$J$9/12*'Staff P&L'!$T$9+'Staff P&L'!$J$11/12*'Staff P&L'!$T$11+IFERROR('Staff P&L'!$G$25/'Staff P&L'!$H$25*'Staff P&L'!$I$25,0) -> 3841.5313 | N18: =SUM(B18:M18) -> 39325.983 | P18: Employer AZ/US tax on COGS wages
A19: Benefits - PEO | B19: =IF(1>=Benefits!$B$43,Benefits!$F$19*'Staff P&L'!$T$6+Benefits!$F$20*'Staff P&L'!$T$7+Benefits!$F$21*'Staff P&L'!$T$8+Benefits!$F$22*'Staff P&L'!$T$9+Benefits!$F$24*'Staff P&L'!$T$11,0) -> 0 | C19: =IF(2>=Benefits!$B$43,Benefits!$F$19*'Staff P&L'!$T$6+Benefits!$F$20*'Staff P&L'!$T$7+Benefits!$F$21*'Staff P&L'!$T$8+Benefits!$F$22*'Staff P&L'!$T$9+Benefits!$F$24*'Staff P&L'!$T$11,0) -> 0 | D19: =IF(3>=Benefits!$B$43,Benefits!$F$19*'Staff P&L'!$T$6+Benefits!$F$20*'Staff P&L'!$T$7+Benefits!$F$21*'Staff P&L'!$T$8+Benefits!$F$22*'Staff P&L'!$T$9+Benefits!$F$24*'Staff P&L'!$T$11,0) -> 0 | E19: =IF(4>=Benefits!$B$43,Benefits!$F$19*'Staff P&L'!$T$6+Benefits!$F$20*'Staff P&L'!$T$7+Benefits!$F$21*'Staff P&L'!$T$8+Benefits!$F$22*'Staff P&L'!$T$9+Benefits!$F$24*'Staff P&L'!$T$11,0) -> 0 | F19: =IF(5>=Benefits!$B$43,Benefits!$F$19*'Staff P&L'!$T$6+Benefits!$F$20*'Staff P&L'!$T$7+Benefits!$F$21*'Staff P&L'!$T$8+Benefits!$F$22*'Staff P&L'!$T$9+Benefits!$F$24*'Staff P&L'!$T$11,0) -> 0 | G19: =IF(6>=Benefits!$B$43,Benefits!$F$19*'Staff P&L'!$T$6+Benefits!$F$20*'Staff P&L'!$T$7+Benefits!$F$21*'Staff P&L'!$T$8+Benefits!$F$22*'Staff P&L'!$T$9+Benefits!$F$24*'Staff P&L'!$T$11,0) -> 0 | H19: =IF(7>=Benefits!$B$43,Benefits!$F$19*'Staff P&L'!$T$6+Benefits!$F$20*'Staff P&L'!$T$7+Benefits!$F$21*'Staff P&L'!$T$8+Benefits!$F$22*'Staff P&L'!$T$9+Benefits!$F$24*'Staff P&L'!$T$11,0) -> 0 | I19: =IF(8>=Benefits!$B$43,Benefits!$F$19*'Staff P&L'!$T$6+Benefits!$F$20*'Staff P&L'!$T$7+Benefits!$F$21*'Staff P&L'!$T$8+Benefits!$F$22*'Staff P&L'!$T$9+Benefits!$F$24*'Staff P&L'!$T$11,0) -> 0 | J19: =IF(9>=Benefits!$B$43,Benefits!$F$19*'Staff P&L'!$T$6+Benefits!$F$20*'Staff P&L'!$T$7+Benefits!$F$21*'Staff P&L'!$T$8+Benefits!$F$22*'Staff P&L'!$T$9+Benefits!$F$24*'Staff P&L'!$T$11,0) -> 0 | K19: =IF(10>=Benefits!$B$43,Benefits!$F$19*'Staff P&L'!$T$6+Benefits!$F$20*'Staff P&L'!$T$7+Benefits!$F$21*'Staff P&L'!$T$8+Benefits!$F$22*'Staff P&L'!$T$9+Benefits!$F$24*'Staff P&L'!$T$11,0) -> 0 | L19: =IF(11>=Benefits!$B$43,Benefits!$F$19*'Staff P&L'!$T$6+Benefits!$F$20*'Staff P&L'!$T$7+Benefits!$F$21*'Staff P&L'!$T$8+Benefits!$F$22*'Staff P&L'!$T$9+Benefits!$F$24*'Staff P&L'!$T$11,0) -> 5327.5145 | M19: =IF(12>=Benefits!$B$43,Benefits!$F$19*'Staff P&L'!$T$6+Benefits!$F$20*'Staff P&L'!$T$7+Benefits!$F$21*'Staff P&L'!$T$8+Benefits!$F$22*'Staff P&L'!$T$9+Benefits!$F$24*'Staff P&L'!$T$11,0) -> 5327.5145 | N19: =SUM(B19:M19) -> 10655.029 | P19: PEO insurance/401k, COGS-allocated
A20: Total for Payroll Expenses | B20: =B15+B16+B17+B18+B19 -> 44118.459 | C20: =C15+C16+C17+C18+C19 -> 42518.459 | D20: =D15+D16+D17+D18+D19 -> 44118.459 | E20: =E15+E16+E17+E18+E19 -> 44118.459 | F20: =F15+F16+F17+F18+F19 -> 43318.459 | G20: =G15+G16+G17+G18+G19 -> 44118.459 | H20: =H15+H16+H17+H18+H19 -> 44918.459 | I20: =I15+I16+I17+I18+I19 -> 43318.459 | ... N20: =N15+N16+N17+N18+N19 -> 579612.24
A21: Total for Cost of Goods Sold | B21: =B12+B13+B20 -> 48346.939 | C21: =C12+C13+C20 -> 46746.939 | D21: =D12+D13+D20 -> 48346.939 | E21: =E12+E13+E20 -> 48346.939 | F21: =F12+F13+F20 -> 47546.939 | G21: =G12+G13+G20 -> 48346.939 | H21: =H12+H13+H20 -> 49146.939 | I21: =I12+I13+I20 -> 47546.939 | ... N21: =N12+N13+N20 -> 630354
A22: Gross Profit | B22: =B10-B21 -> 48002.243 | C22: =C10-C21 -> 44322.821 | D22: =D10-D21 -> 53281.666 | E22: =E10-E21 -> 53281.666 | F22: =F10-F21 -> 43522.821 | G22: =G10-G21 -> 53281.666 | H22: =H10-H21 -> 52481.666 | I22: =I10-I21 -> 51802.243 | ... N22: =N10-N21 -> 615628.94
A23: Expenses
A24: Owner Compensation (Steven, admin 50%) | B24: ='Staff P&L'!$E$6/12*(1-'Staff P&L'!$T$6) -> 7687.5 | C24: ='Staff P&L'!$E$6/12*(1-'Staff P&L'!$T$6) -> 7687.5 | D24: ='Staff P&L'!$E$6/12*(1-'Staff P&L'!$T$6) -> 7687.5 | E24: ='Staff P&L'!$E$6/12*(1-'Staff P&L'!$T$6) -> 7687.5 | F24: ='Staff P&L'!$E$6/12*(1-'Staff P&L'!$T$6) -> 7687.5 | G24: ='Staff P&L'!$E$6/12*(1-'Staff P&L'!$T$6) -> 7687.5 | H24: ='Staff P&L'!$E$6/12*(1-'Staff P&L'!$T$6) -> 7687.5 | I24: ='Staff P&L'!$E$6/12*(1-'Staff P&L'!$T$6) -> 7687.5 | ... M24: ='Staff P&L'!$E$6/12*(1-'Staff P&L'!$T$6) -> 7687.5 | N24: =SUM(B24:M24) -> 92250 | P24: Owner salary, admin share
A25: Admin Salary (Josephine) | B25: ='Staff P&L'!$E$11/12*(1-'Staff P&L'!$T$11) -> 5666.6667 | C25: ='Staff P&L'!$E$11/12*(1-'Staff P&L'!$T$11) -> 5666.6667 | D25: ='Staff P&L'!$E$11/12*(1-'Staff P&L'!$T$11) -> 5666.6667 | E25: ='Staff P&L'!$E$11/12*(1-'Staff P&L'!$T$11) -> 5666.6667 | F25: ='Staff P&L'!$E$11/12*(1-'Staff P&L'!$T$11) -> 5666.6667 | G25: ='Staff P&L'!$E$11/12*(1-'Staff P&L'!$T$11) -> 5666.6667 | H25: ='Staff P&L'!$E$11/12*(1-'Staff P&L'!$T$11) -> 5666.6667 | I25: ='Staff P&L'!$E$11/12*(1-'Staff P&L'!$T$11) -> 5666.6667 | ... M25: ='Staff P&L'!$E$11/12*(1-'Staff P&L'!$T$11) -> 5666.6667 | N25: =SUM(B25:M25) -> 68000 | P25: Admin share of $80k
A26: Admin Payroll Taxes | B26: ='Staff P&L'!$J$6/12*(1-'Staff P&L'!$T$6)+'Staff P&L'!$J$11/12*(1-'Staff P&L'!$T$11) -> 1038.8287 | C26: ='Staff P&L'!$J$6/12*(1-'Staff P&L'!$T$6)+'Staff P&L'!$J$11/12*(1-'Staff P&L'!$T$11) -> 1038.8287 | D26: ='Staff P&L'!$J$6/12*(1-'Staff P&L'!$T$6)+'Staff P&L'!$J$11/12*(1-'Staff P&L'!$T$11) -> 1038.8287 | E26: ='Staff P&L'!$J$6/12*(1-'Staff P&L'!$T$6)+'Staff P&L'!$J$11/12*(1-'Staff P&L'!$T$11) -> 1038.8287 | F26: ='Staff P&L'!$J$6/12*(1-'Staff P&L'!$T$6)+'Staff P&L'!$J$11/12*(1-'Staff P&L'!$T$11) -> 1038.8287 | G26: ='Staff P&L'!$J$6/12*(1-'Staff P&L'!$T$6)+'Staff P&L'!$J$11/12*(1-'Staff P&L'!$T$11) -> 1038.8287 | H26: ='Staff P&L'!$J$6/12*(1-'Staff P&L'!$T$6)+'Staff P&L'!$J$11/12*(1-'Staff P&L'!$T$11) -> 1038.8287 | I26: ='Staff P&L'!$J$6/12*(1-'Staff P&L'!$T$6)+'Staff P&L'!$J$11/12*(1-'Staff P&L'!$T$11) -> 1038.8287 | ... M26: ='Staff P&L'!$J$6/12*(1-'Staff P&L'!$T$6)+'Staff P&L'!$J$11/12*(1-'Staff P&L'!$T$11) -> 1038.8287 | N26: =SUM(B26:M26) -> 12465.945
A27: Admin Benefits - PEO | B27: =IF(1>=Benefits!$B$43,Benefits!$F$19*(1-'Staff P&L'!$T$6)+Benefits!$F$24*(1-'Staff P&L'!$T$11),0) -> 0 | C27: =IF(2>=Benefits!$B$43,Benefits!$F$19*(1-'Staff P&L'!$T$6)+Benefits!$F$24*(1-'Staff P&L'!$T$11),0) -> 0 | D27: =IF(3>=Benefits!$B$43,Benefits!$F$19*(1-'Staff P&L'!$T$6)+Benefits!$F$24*(1-'Staff P&L'!$T$11),0) -> 0 | E27: =IF(4>=Benefits!$B$43,Benefits!$F$19*(1-'Staff P&L'!$T$6)+Benefits!$F$24*(1-'Staff P&L'!$T$11),0) -> 0 | F27: =IF(5>=Benefits!$B$43,Benefits!$F$19*(1-'Staff P&L'!$T$6)+Benefits!$F$24*(1-'Staff P&L'!$T$11),0) -> 0 | G27: =IF(6>=Benefits!$B$43,Benefits!$F$19*(1-'Staff P&L'!$T$6)+Benefits!$F$24*(1-'Staff P&L'!$T$11),0) -> 0 | H27: =IF(7>=Benefits!$B$43,Benefits!$F$19*(1-'Staff P&L'!$T$6)+Benefits!$F$24*(1-'Staff P&L'!$T$11),0) -> 0 | I27: =IF(8>=Benefits!$B$43,Benefits!$F$19*(1-'Staff P&L'!$T$6)+Benefits!$F$24*(1-'Staff P&L'!$T$11),0) -> 0 | J27: =IF(9>=Benefits!$B$43,Benefits!$F$19*(1-'Staff P&L'!$T$6)+Benefits!$F$24*(1-'Staff P&L'!$T$11),0) -> 0 | K27: =IF(10>=Benefits!$B$43,Benefits!$F$19*(1-'Staff P&L'!$T$6)+Benefits!$F$24*(1-'Staff P&L'!$T$11),0) -> 0 | L27: =IF(11>=Benefits!$B$43,Benefits!$F$19*(1-'Staff P&L'!$T$6)+Benefits!$F$24*(1-'Staff P&L'!$T$11),0) -> 1639.1855 | M27: =IF(12>=Benefits!$B$43,Benefits!$F$19*(1-'Staff P&L'!$T$6)+Benefits!$F$24*(1-'Staff P&L'!$T$11),0) -> 1639.1855 | N27: =SUM(B27:M27) -> 3278.371
A28: Advertising & Marketing | B28: 56.33 | C28: 56.33 | D28: 56.33 | E28: 56.33 | F28: 56.33 | G28: 56.33 | H28: 56.33 | I28: 56.33 | J28: 56.33 | K28: 56.33 | L28: 56.33 | M28: 56.33 | N28: =SUM(B28:M28) -> 675.96 | P28: H1-26 monthly avg — review
A29: Bank Charges & Fees | B29: 35.42 | C29: 35.42 | D29: 35.42 | E29: 35.42 | F29: 35.42 | G29: 35.42 | H29: 35.42 | I29: 35.42 | J29: 35.42 | K29: 35.42 | L29: 35.42 | M29: 35.42 | N29: =SUM(B29:M29) -> 425.04 | P29: H1-26 monthly avg — review
A30: Dues & subscriptions | B30: 118 | C30: 118 | D30: 118 | E30: 118 | F30: 118 | G30: 118 | H30: 118 | I30: 118 | J30: 118 | K30: 118 | L30: 118 | M30: 118 | N30: =SUM(B30:M30) -> 1416 | P30: H1-26 monthly avg — review
A31: Insurance | B31: 171.66 | C31: 171.66 | D31: 171.66 | E31: 171.66 | F31: 171.66 | G31: 171.66 | H31: 171.66 | I31: 171.66 | J31: 171.66 | K31: 171.66 | L31: 171.66 | M31: 171.66 | N31: =SUM(B31:M31) -> 2059.92 | P31: H1-26 monthly avg — review
A32: IT | B32: =1000*1.15 -> 1150 | C32: =1000*1.15 -> 1150 | D32: =1000*1.15 -> 1150 | E32: =1000*1.15 -> 1150 | F32: =1000*1.15 -> 1150 | G32: =1000*1.15 -> 1150 | H32: =1000*1.15 -> 1150 | I32: =1000*1.15 -> 1150 | ... M32: =1000*1.15 -> 1150 | N32: =SUM(B32:M32) -> 13800
A33: Legal & Professional Services | B33: 1813.98 | C33: 1813.98 | D33: 1813.98 | E33: 1813.98 | F33: 1813.98 | G33: 1813.98 | H33: 1813.98 | I33: 1813.98 | J33: 1813.98 | K33: 1813.98 | L33: 1813.98 | M33: 1813.98 | N33: =SUM(B33:M33) -> 21767.76 | P33: H1-26 monthly avg — review
A34: Meals & Entertainment | B34: 420.88 | C34: 420.88 | D34: 420.88 | E34: 420.88 | F34: 420.88 | G34: 420.88 | H34: 420.88 | I34: 420.88 | J34: 420.88 | K34: 420.88 | L34: 420.88 | M34: 420.88 | N34: =SUM(B34:M34) -> 5050.56 | P34: H1-26 monthly avg — review
A35: Office Supplies & Software | B35: 2408.73 | C35: 2408.73 | D35: 2408.73 | E35: 2408.73 | F35: 2408.73 | G35: 2408.73 | H35: 2408.73 | I35: 2408.73 | J35: 2408.73 | K35: 2408.73 | L35: 2408.73 | M35: 2408.73 | N35: =SUM(B35:M35) -> 28904.76 | P35: H1-26 monthly avg — review
A36: QuickBooks Payments Fees | B36: 224.18 | C36: 224.18 | D36: 224.18 | E36: 224.18 | F36: 224.18 | G36: 224.18 | H36: 224.18 | I36: 224.18 | J36: 224.18 | K36: 224.18 | L36: 224.18 | M36: 224.18 | N36: =SUM(B36:M36) -> 2690.16 | P36: H1-26 monthly avg — review
A37: Reimbursements | B37: 11.22 | C37: 11.22 | D37: 11.22 | E37: 11.22 | F37: 11.22 | G37: 11.22 | H37: 11.22 | I37: 11.22 | J37: 11.22 | K37: 11.22 | L37: 11.22 | M37: 11.22 | N37: =SUM(B37:M37) -> 134.64 | P37: H1-26 monthly avg — review
A38: Rent & Lease | B38: 1200 | C38: 1200 | D38: 1200 | E38: 1200 | F38: 1200 | G38: 1200 | H38: 1200 | I38: 1200 | J38: 1200 | K38: 1200 | L38: 1200 | M38: 1200 | N38: =SUM(B38:M38) -> 14400 | P38: H1-26 monthly avg — review
A39: Website | B39: 34.56 | C39: 34.56 | D39: 34.56 | E39: 34.56 | F39: 34.56 | G39: 34.56 | H39: 34.56 | I39: 34.56 | J39: 34.56 | K39: 34.56 | L39: 34.56 | M39: 34.56 | N39: =SUM(B39:M39) -> 414.72 | P39: H1-26 monthly avg — review
A40: Total for Expenses | B40: =B24+B25+B26+B27+B28+B29+B30+B31+B32+B33+B34+B35+B36+B37+B38+B39 -> 22037.955 | C40: =C24+C25+C26+C27+C28+C29+C30+C31+C32+C33+C34+C35+C36+C37+C38+C39 -> 22037.955 | D40: =D24+D25+D26+D27+D28+D29+D30+D31+D32+D33+D34+D35+D36+D37+D38+D39 -> 22037.955 | E40: =E24+E25+E26+E27+E28+E29+E30+E31+E32+E33+E34+E35+E36+E37+E38+E39 -> 22037.955 | F40: =F24+F25+F26+F27+F28+F29+F30+F31+F32+F33+F34+F35+F36+F37+F38+F39 -> 22037.955 | G40: =G24+G25+G26+G27+G28+G29+G30+G31+G32+G33+G34+G35+G36+G37+G38+G39 -> 22037.955 | H40: =H24+H25+H26+H27+H28+H29+H30+H31+H32+H33+H34+H35+H36+H37+H38+H39 -> 22037.955 | I40: =I24+I25+I26+I27+I28+I29+I30+I31+I32+I33+I34+I35+I36+I37+I38+I39 -> 22037.955 | ... N40: =N24+N25+N26+N27+N28+N29+N30+N31+N32+N33+N34+N35+N36+N37+N38+N39 -> 267733.84
A41: Net Operating Income | B41: =B22-B40 -> 25964.288 | C41: =C22-C40 -> 22284.865 | D41: =D22-D40 -> 31243.711 | E41: =E22-E40 -> 31243.711 | F41: =F22-F40 -> 21484.865 | G41: =G22-G40 -> 31243.711 | H41: =H22-H40 -> 30443.711 | I41: =I22-I40 -> 29764.288 | ... N41: =N22-N40 -> 347895.1
A42: Net Income | B42: =B41 -> 25964.288 | C42: =C41 -> 22284.865 | D42: =D41 -> 31243.711 | E42: =E41 -> 31243.711 | F42: =F41 -> 21484.865 | G42: =G41 -> 31243.711 | H42: =H41 -> 30443.711 | I42: =I41 -> 29764.288 | ... N42: =N41 -> 347895.1
A45: LABOR BURDEN — LOADED COST PER HOUR (from Staff P&L)
A46: Employee | B46: Loaded $/yr | C46: Loaded $/mo | D46: Loaded $/hr | E46: Bill rate
A47: ='Staff P&L'!$A$6 -> Steven Nikolov | B47: ='Staff P&L'!$M$6 -> 202910.43 | C47: ='Staff P&L'!$N$6 -> 16909.202 | D47: ='Staff P&L'!$O$6 -> 97.179325 | E47: ='Staff P&L'!$R$6 -> 246.57126
A48: ='Staff P&L'!$A$7 -> Lisa Danforth | B48: ='Staff P&L'!$M$7 -> 193717.68 | C48: ='Staff P&L'!$N$7 -> 16143.14 | D48: ='Staff P&L'!$O$7 -> 92.776667 | E48: ='Staff P&L'!$R$7 -> 246.57126
A49: ='Staff P&L'!$A$8 -> Jessica Bumphus | B49: ='Staff P&L'!$M$8 -> 137849.74 | C49: ='Staff P&L'!$N$8 -> 11487.478 | D49: ='Staff P&L'!$O$8 -> 66.01999 | E49: ='Staff P&L'!$R$8 -> 151.11296
A50: ='Staff P&L'!$A$9 -> Christine Johnson | B50: ='Staff P&L'!$M$9 -> 94197.218 | C50: ='Staff P&L'!$N$9 -> 7849.7682 | D50: ='Staff P&L'!$O$9 -> 45.11361 | E50: ='Staff P&L'!$R$9 -> 94.988641
A51: ='Staff P&L'!$A$10 -> Valentina Dikova | B51: ='Staff P&L'!$M$10 -> 50400 | C51: ='Staff P&L'!$N$10 -> 4200 | D51: ='Staff P&L'!$O$10 -> 24.137931 | E51: ='Staff P&L'!$R$10 -> 94.988641
A52: ='Staff P&L'!$A$11 -> Josephine Mack | B52: ='Staff P&L'!$M$11 -> 104055.86 | C52: ='Staff P&L'!$N$11 -> 8671.3217 | D52: ='Staff P&L'!$O$11 -> 49.835182 | E52: ='Staff P&L'!$R$11 -> 94.988641

Sheet Forecast 2026
A1: Onyx Accounting Group, LLC
A2: Budget & Forecast 2026
A3: January–July are the actual figures from the QuickBooks P&L (cash basis). August–December are calculated from the budget.
A5: Utilization (Aug–Dec only) | B5: =Assumptions!$B$15 -> 0.91 | C5: =IF(SUM('Budget P&L'!$B$9:$H$9)=0,0,SUM(B11:H11)/(SUM('Budget P&L'!$B$9:$H$9)/Assumptions!$B$15)) -> 0.91769661 | D5: ← left: the toggle (edit here or on Assumptions!B15). right: utilization implied by Jan–Jul actuals — set the toggle to this to carry the actual run-rate forward.
B7: Jan 2026 | C7: Feb 2026 | D7: Mar 2026 | E7: Apr 2026 | F7: May 2026 | G7: Jun 2026 | H7: Jul 2026 | I7: Aug 2026 | J7: Sep 2026 | K7: Oct 2026 | L7: Nov 2026 | M7: Dec 2026 | N7: Total 2026
B8: ACTUAL | C8: ACTUAL | D8: ACTUAL | E8: ACTUAL | F8: ACTUAL | G8: ACTUAL | H8: ACTUAL | I8: BUDGET | J8: BUDGET | K8: BUDGET | L8: BUDGET | M8: BUDGET
A9: INCOME
A10: Billable Expense Income | B10: 0 | C10: 46.75 | D10: 21 | E10: 0 | F10: 2294 | G10: -418 | H10: -152.69 | I10: ='Budget P&L'!I8 -> 0 | J10: ='Budget P&L'!J8 -> 0 | K10: ='Budget P&L'!K8 -> 0 | L10: ='Budget P&L'!L8 -> 0 | M10: ='Budget P&L'!M8 -> 0 | N10: =SUM(B10:M10) -> 1791.06
A11: Sales | B11: 64981.75 | C11: 55772 | D11: 103377.75 | E11: 88464.25 | F11: 97011.45 | G11: 104042 | H11: 177147.55 | I11: ='Budget P&L'!I9 -> 99349.182 | J11: ='Budget P&L'!J9 -> 102349.18 | K11: ='Budget P&L'!K9 -> 122685.83 | L11: ='Budget P&L'!L9 -> 113835.14 | M11: ='Budget P&L'!M9 -> 122760.48 | N11: =SUM(B11:M11) -> 1251776.6
A12: Unapplied Cash Payment Income | B12: -154.75 | C12: 0 | D12: 0 | E12: 1000 | F12: 875 | G12: -1500 | H12: -375 | I12: 0 | J12: 0 | K12: 0 | L12: 0 | M12: 0 | N12: =SUM(B12:M12) -> -154.75
A13: Total Income | B13: =SUM(B10:B12) -> 64827 | C13: =SUM(C10:C12) -> 55818.75 | D13: =SUM(D10:D12) -> 103398.75 | E13: =SUM(E10:E12) -> 89464.25 | F13: =SUM(F10:F12) -> 100180.45 | G13: =SUM(G10:G12) -> 102124 | H13: =SUM(H10:H12) -> 176619.86 | I13: =SUM(I10:I12) -> 99349.182 | ... N13: =SUM(N10:N12) -> 1253412.9
A14: COST OF GOODS SOLD
A15: Cost of labor - Contractors | B15: 1498.5 | C15: 430 | D15: 355.5 | E15: 1089.5 | F15: 0 | G15: 0 | H15: 0 | I15: ='Budget P&L'!I12 -> 4200 | J15: ='Budget P&L'!J12 -> 4200 | K15: ='Budget P&L'!K12 -> 4200 | L15: ='Budget P&L'!L12 -> 4200 | M15: ='Budget P&L'!M12 -> 4200 | N15: =SUM(B15:M15) -> 24373.5
A16: Filing Fees | B16: 94.5 | C16: 0 | D16: 13.2 | E16: 63.2 | F16: 0 | G16: 0 | H16: 0 | I16: ='Budget P&L'!I13 -> 28.48 | J16: ='Budget P&L'!J13 -> 28.48 | K16: ='Budget P&L'!K13 -> 28.48 | L16: ='Budget P&L'!L13 -> 28.48 | M16: ='Budget P&L'!M13 -> 28.48 | N16: =SUM(B16:M16) -> 313.3
A17: Discretionary Bonuses | B17: 0 | C17: 435 | D17: 435 | E17: 435 | F17: 870 | G17: 435 | H17: 0 | I17: ='Budget P&L'!I15 -> 0 | J17: ='Budget P&L'!J15 -> 8852.8 | K17: ='Budget P&L'!K15 -> 0 | L17: ='Budget P&L'!L15 -> 0 | M17: ='Budget P&L'!M15 -> 8852.8 | N17: =SUM(B17:M17) -> 20315.6
A18: Holiday Pay | B18: 4320 | C18: 0 | D18: 0 | E18: 0 | F18: 280 | G18: 760 | H18: 760 | I18: ='Budget P&L'!I16 -> 0 | J18: ='Budget P&L'!J16 -> 0 | K18: ='Budget P&L'!K16 -> 0 | L18: ='Budget P&L'!L16 -> 0 | M18: ='Budget P&L'!M16 -> 0 | N18: =SUM(B18:M18) -> 6120
A19: Wages | B19: 18160.3 | C19: 33566.6 | D19: 37053.6 | E19: 33728.59 | F19: 46769.76 | G19: 64034.11 | H19: 91281.34 | I19: ='Budget P&L'!I17 -> 40154.167 | J19: ='Budget P&L'!J17 -> 40954.167 | K19: ='Budget P&L'!K17 -> 48579.375 | L19: ='Budget P&L'!L17 -> 47779.375 | M19: ='Budget P&L'!M17 -> 49379.375 | N19: =SUM(B19:M19) -> 551440.76
A20: Payroll Taxes | B20: 2271.72 | C20: 2808.37 | D20: 2893.57 | E20: 2750.47 | F20: 3979.19 | G20: 5164.66 | H20: 7041.14 | I20: ='Budget P&L'!I18 -> 3164.2921 | J20: ='Budget P&L'!J18 -> 3841.5313 | K20: ='Budget P&L'!K18 -> 3164.2921 | L20: ='Budget P&L'!L18 -> 3164.2921 | M20: ='Budget P&L'!M18 -> 3841.5313 | N20: =SUM(B20:M20) -> 44085.059
A21: Benefits - PEO | B21: 0 | C21: 0 | D21: 0 | E21: 0 | F21: 0 | G21: 0 | H21: 0 | I21: ='Budget P&L'!I19 -> 0 | J21: ='Budget P&L'!J19 -> 0 | K21: ='Budget P&L'!K19 -> 0 | L21: ='Budget P&L'!L19 -> 5327.5145 | M21: ='Budget P&L'!M19 -> 5327.5145 | N21: =SUM(B21:M21) -> 10655.029
A22: Total Cost of Goods Sold | B22: =SUM(B15:B21) -> 26345.02 | C22: =SUM(C15:C21) -> 37239.97 | D22: =SUM(D15:D21) -> 40750.87 | E22: =SUM(E15:E21) -> 38066.76 | F22: =SUM(F15:F21) -> 51898.95 | G22: =SUM(G15:G21) -> 70393.77 | H22: =SUM(H15:H21) -> 99082.48 | I22: =SUM(I15:I21) -> 47546.939 | ... N22: =SUM(N15:N21) -> 657303.25
A23: GROSS PROFIT | B23: =B13-B22 -> 38481.98 | C23: =C13-C22 -> 18578.78 | D23: =D13-D22 -> 62647.88 | E23: =E13-E22 -> 51397.49 | F23: =F13-F22 -> 48281.5 | G23: =G13-G22 -> 31730.23 | H23: =H13-H22 -> 77537.38 | I23: =I13-I22 -> 51802.243 | ... N23: =N13-N22 -> 596109.63
A24: OPERATING EXPENSES
A25: Owner Compensation (Steven, admin 50%) | B25: 0 | C25: 0 | D25: 0 | E25: 0 | F25: 0 | G25: 0 | H25: 0 | I25: ='Budget P&L'!I24 -> 7687.5 | J25: ='Budget P&L'!J24 -> 7687.5 | K25: ='Budget P&L'!K24 -> 7687.5 | L25: ='Budget P&L'!L24 -> 7687.5 | M25: ='Budget P&L'!M24 -> 7687.5 | N25: =SUM(B25:M25) -> 38437.5
A26: Admin Salary (Josephine) | B26: 0 | C26: 0 | D26: 0 | E26: 0 | F26: 0 | G26: 0 | H26: 0 | I26: ='Budget P&L'!I25 -> 5666.6667 | J26: ='Budget P&L'!J25 -> 5666.6667 | K26: ='Budget P&L'!K25 -> 5666.6667 | L26: ='Budget P&L'!L25 -> 5666.6667 | M26: ='Budget P&L'!M25 -> 5666.6667 | N26: =SUM(B26:M26) -> 28333.333
A27: Admin Payroll Taxes | B27: 0 | C27: 0 | D27: 0 | E27: 0 | F27: 0 | G27: 0 | H27: 0 | I27: ='Budget P&L'!I26 -> 1038.8287 | J27: ='Budget P&L'!J26 -> 1038.8287 | K27: ='Budget P&L'!K26 -> 1038.8287 | L27: ='Budget P&L'!L26 -> 1038.8287 | M27: ='Budget P&L'!M26 -> 1038.8287 | N27: =SUM(B27:M27) -> 5194.1438
A28: Admin Benefits - PEO | B28: 0 | C28: 0 | D28: 0 | E28: 0 | F28: 0 | G28: 0 | H28: 0 | I28: ='Budget P&L'!I27 -> 0 | J28: ='Budget P&L'!J27 -> 0 | K28: ='Budget P&L'!K27 -> 0 | L28: ='Budget P&L'!L27 -> 1639.1855 | M28: ='Budget P&L'!M27 -> 1639.1855 | N28: =SUM(B28:M28) -> 3278.371
A29: Advertising & Marketing | B29: 0 | C29: 0 | D29: 0 | E29: 0 | F29: 0 | G29: 338 | H29: 590.36 | I29: ='Budget P&L'!I28 -> 56.33 | J29: ='Budget P&L'!J28 -> 56.33 | K29: ='Budget P&L'!K28 -> 56.33 | L29: ='Budget P&L'!L28 -> 56.33 | M29: ='Budget P&L'!M28 -> 56.33 | N29: =SUM(B29:M29) -> 1210.01
A30: Bank Charges & Fees | B30: 9.6 | C30: 5 | D30: 4 | E30: 48.99 | F30: 71.42 | G30: 73.52 | H30: 68.63 | I30: ='Budget P&L'!I29 -> 35.42 | J30: ='Budget P&L'!J29 -> 35.42 | K30: ='Budget P&L'!K29 -> 35.42 | L30: ='Budget P&L'!L29 -> 35.42 | M30: ='Budget P&L'!M29 -> 35.42 | N30: =SUM(B30:M30) -> 458.26
A31: Dues & subscriptions | B31: 100 | C31: 100 | D31: 100 | E31: 100 | F31: 185 | G31: 122.99 | H31: 252.57 | I31: ='Budget P&L'!I30 -> 118 | J31: ='Budget P&L'!J30 -> 118 | K31: ='Budget P&L'!K30 -> 118 | L31: ='Budget P&L'!L30 -> 118 | M31: ='Budget P&L'!M30 -> 118 | N31: =SUM(B31:M31) -> 1550.56
A32: Insurance | B32: 148.98 | C32: 163.14 | D32: 203.88 | E32: 171.34 | F32: 168.44 | G32: 174.18 | H32: 194.18 | I32: ='Budget P&L'!I31 -> 171.66 | J32: ='Budget P&L'!J31 -> 171.66 | K32: ='Budget P&L'!K31 -> 171.66 | L32: ='Budget P&L'!L31 -> 171.66 | M32: ='Budget P&L'!M31 -> 171.66 | N32: =SUM(B32:M32) -> 2082.44
A33: IT | B33: 0 | C33: 0 | D33: 0 | E33: 0 | F33: 0 | G33: 0 | H33: 0 | I33: ='Budget P&L'!I32 -> 1150 | J33: ='Budget P&L'!J32 -> 1150 | K33: ='Budget P&L'!K32 -> 1150 | L33: ='Budget P&L'!L32 -> 1150 | M33: ='Budget P&L'!M32 -> 1150 | N33: =SUM(B33:M33) -> 5750
A34: Legal & Professional Services | B34: 399.75 | C34: 293.25 | D34: 1471.25 | E34: 0 | F34: 3419.63 | G34: 5300 | H34: 5200 | I34: ='Budget P&L'!I33 -> 1813.98 | J34: ='Budget P&L'!J33 -> 1813.98 | K34: ='Budget P&L'!K33 -> 1813.98 | L34: ='Budget P&L'!L33 -> 1813.98 | M34: ='Budget P&L'!M33 -> 1813.98 | N34: =SUM(B34:M34) -> 25153.78
A35: Meals & Entertainment | B35: 539.3 | C35: 439.55 | D35: 319.77 | E35: 486.47 | F35: 579.59 | G35: 160.62 | H35: 202.85 | I35: ='Budget P&L'!I34 -> 420.88 | J35: ='Budget P&L'!J34 -> 420.88 | K35: ='Budget P&L'!K34 -> 420.88 | L35: ='Budget P&L'!L34 -> 420.88 | M35: ='Budget P&L'!M34 -> 420.88 | N35: =SUM(B35:M35) -> 4832.55
A36: Office Supplies & Software | B36: 2705.65 | C36: 1598.23 | D36: 2648.42 | E36: 3059.94 | F36: 1942.95 | G36: 2497.17 | H36: 3145.14 | I36: ='Budget P&L'!I35 -> 2408.73 | J36: ='Budget P&L'!J35 -> 2408.73 | K36: ='Budget P&L'!K35 -> 2408.73 | L36: ='Budget P&L'!L35 -> 2408.73 | M36: ='Budget P&L'!M35 -> 2408.73 | N36: =SUM(B36:M36) -> 29641.15
A37: PTO-1 | B37: 1630 | C37: 340 | D37: 280 | E37: 1790 | F37: 4096 | G37: 280 | H37: 0 | I37: 0 | J37: 0 | K37: 0 | L37: 0 | M37: 0 | N37: =SUM(B37:M37) -> 8416
A38: QuickBooks Payments Fees | B38: 162.91 | C38: 244.59 | D38: 295.51 | E38: 91.12 | F38: 222.15 | G38: 328.8 | H38: 404.14 | I38: ='Budget P&L'!I36 -> 224.18 | J38: ='Budget P&L'!J36 -> 224.18 | K38: ='Budget P&L'!K36 -> 224.18 | L38: ='Budget P&L'!L36 -> 224.18 | M38: ='Budget P&L'!M36 -> 224.18 | N38: =SUM(B38:M38) -> 2870.12
A39: Reimbursements | B39: 0 | C39: 12 | D39: 0 | E39: 0 | F39: 55.35 | G39: 0 | H39: 0 | I39: ='Budget P&L'!I37 -> 11.22 | J39: ='Budget P&L'!J37 -> 11.22 | K39: ='Budget P&L'!K37 -> 11.22 | L39: ='Budget P&L'!L37 -> 11.22 | M39: ='Budget P&L'!M37 -> 11.22 | N39: =SUM(B39:M39) -> 123.45
A40: Rent & Lease | B40: 1200 | C40: 1200 | D40: 1200 | E40: 1200 | F40: 1200 | G40: 1200 | H40: 1200 | I40: ='Budget P&L'!I38 -> 1200 | J40: ='Budget P&L'!J38 -> 1200 | K40: ='Budget P&L'!K38 -> 1200 | L40: ='Budget P&L'!L38 -> 1200 | M40: ='Budget P&L'!M38 -> 1200 | N40: =SUM(B40:M40) -> 14400
A41: Unapplied Cash Bill Payment Expense | B41: 0 | C41: 0 | D41: 0 | E41: 0 | F41: 0 | G41: 0 | H41: 0 | I41: 0 | J41: 0 | K41: 0 | L41: 0 | M41: 0 | N41: =SUM(B41:M41) -> 0
A42: Website | B42: 0 | C42: 0 | D42: 0 | E42: 207.36 | F42: 0 | G42: 0 | H42: 0 | I42: ='Budget P&L'!I39 -> 34.56 | J42: ='Budget P&L'!J39 -> 34.56 | K42: ='Budget P&L'!K39 -> 34.56 | L42: ='Budget P&L'!L39 -> 34.56 | M42: ='Budget P&L'!M39 -> 34.56 | N42: =SUM(B42:M42) -> 380.16
A43: Total Operating Expenses | B43: =SUM(B25:B42) -> 6896.19 | C43: =SUM(C25:C42) -> 4395.76 | D43: =SUM(D25:D42) -> 6522.83 | E43: =SUM(E25:E42) -> 7155.22 | F43: =SUM(F25:F42) -> 11940.53 | G43: =SUM(G25:G42) -> 10475.28 | H43: =SUM(H25:H42) -> 11257.87 | I43: =SUM(I25:I42) -> 22037.955 | ... N43: =SUM(N25:N42) -> 172111.83
A44: NET INCOME | B44: =B23-B43 -> 31585.79 | C44: =C23-C43 -> 14183.02 | D44: =D23-D43 -> 56125.05 | E44: =E23-E43 -> 44242.27 | F44: =F23-F43 -> 36340.97 | G44: =G23-G43 -> 21254.95 | H44: =H23-H43 -> 66279.51 | I44: =I23-I43 -> 29764.288 | ... N44: =N23-N43 -> 423997.8
A45: Net margin | B45: =IF(B13=0,0,B44/B13) -> 0.48723202 | C45: =IF(C13=0,0,C44/C13) -> 0.25409061 | D45: =IF(D13=0,0,D44/D13) -> 0.54280202 | E45: =IF(E13=0,0,E44/E13) -> 0.49452457 | F45: =IF(F13=0,0,F44/F13) -> 0.36275511 | G45: =IF(G13=0,0,G44/G13) -> 0.20812884 | H45: =IF(H13=0,0,H44/H13) -> 0.37526646 | I45: =IF(I13=0,0,I44/I13) -> 0.29959268 | ... N45: =IF(N13=0,0,N44/N13) -> 0.33827465
A46: Jan–Jul actual / Aug–Dec budget | B46: =SUM(B44:H44) -> 270011.56 | C46: =SUM(I44:M44) -> 153986.24 | D46: ← the two halves of the year
A48: PRO-FORMA — full-year economics
A49: The Jan–Jul actuals carry no owner compensation, admin salary, PEO benefits or IT, because those are not on the QuickBooks P&L. This restates the full year as if every month bore them.
A50: Net income per the forecast above | N50: =N44 -> 423997.8
A51: Less: Owner compensation, Jan–Jul | N51: =-SUM('Budget P&L'!$B$24:$H$24) -> -53812.5
A52: Less: Admin salary, Jan–Jul | N52: =-SUM('Budget P&L'!$B$25:$H$25) -> -39666.667
A53: Less: Admin payroll taxes, Jan–Jul | N53: =-SUM('Budget P&L'!$B$26:$H$26) -> -7271.8013
A54: Less: Admin PEO benefits, Jan–Jul | N54: =-SUM('Budget P&L'!$B$27:$H$27) -> 0
A55: Less: PEO benefits in COGS, Jan–Jul | N55: =-SUM('Budget P&L'!$B$19:$H$19) -> 0
A56: Less: IT, Jan–Jul | N56: =-SUM('Budget P&L'!$B$32:$H$32) -> -8050
A57: PRO-FORMA NET INCOME (all costs expensed all year) | N57: =N50+SUM(N51:N56) -> 315196.84
A59: • Blue Jan–Jul figures are typed from the QuickBooks P&L (cash basis). Green Aug–Dec figures are formulas from the Budget P&L tab and move with the utilization toggle.
A60: • When August closes, type the actual figures over the August column and change its band label to ACTUAL. Nothing else needs touching.
A61: • Actuals are cash basis and the budget is accrual, so revenue timing is not strictly comparable across the two halves of the year.

Sheet Owner Earnings
B1: Onyx Accounting Group, LLC
B2: Owner Earnings & Tax — Steven Nikolov, 2026
B3: Salary, pass-through income and the tax that follows. Yellow cells are inputs — confirm every tax parameter against current IRS and ADOR figures before relying on this.
B4: NOT TAX ADVICE — a planning model. The rate table below ships with estimates, not filed figures.
B6: 1. ENTITY & FILING ASSUMPTIONS
B7: Entity tax treatment | C7: S-Corporation | E7: An LLC paying its owner a W-2 salary is taxed as an S-corp. If you are taxed as a partnership, owner pay is a guaranteed payment and is subject to SE tax — this tab would need reworking.
B8: Filing status | C8: Married filing jointly | E8: Drives the bracket table and thresholds below.
B9: Owner's share of the firm | C9: 1 | E9: Percent of K-1 income allocated to Steven.
B10: Other household WAGES (spouse W-2) | C10: 0 | E10: Wages only. These count towards the Additional Medicare threshold.
B11: Other household non-wage income | C11: 0 | E11: Interest, dividends, capital gains. Taxable, but NOT subject to Medicare tax.
B13: 2. FIRM RESULT → OWNER'S K-1
B14: Firm net income per Forecast 2026 | C14: ='Forecast 2026'!$N$44 -> 423997.8 | E14: As forecast: Jan–Jul actual, Aug–Dec budget.
B15: Add back: owner salary expensed Aug–Dec | C15: =Assumptions!$B$28/12*5 -> 76875 | E15: The budget months carry 5/12 of the owner's salary — half in COGS wages, half in operating expenses.
B16: Add back: employer payroll tax on it, Aug–Dec | C16: ='Staff P&L'!$J$6/12*5 -> 5944.7708 | E16: The budget months also expense 5/12 of the employer tax on the owner's wages, across the COGS and admin payroll-tax lines. Without this add-back it would be charged twice.
B17: Add back: owner salary AND its employer tax inside the Jan–Jul actuals | C17: 0 | E17: Enter salary plus employer payroll tax combined. Both sit inside the actual COGS Wages and Payroll Taxes lines and cannot be identified from a summary P&L. Left at $0 the model assumes Steven drew no salary Jan–Jul.
B18: Firm profit before owner compensation | C18: =C14+C15+C16+C17 -> 506817.57 | E18: Genuinely before owner salary AND its employer tax — both are removed once, below.
B19: Less: owner W-2 salary (full year) | C19: =-Assumptions!$B$28 -> -184500 | E19: Set on Assumptions!B28. Currently the Social Security wage-base max.
B20: Less: employer payroll tax on owner salary | C20: =-'Staff P&L'!$J$6 -> -14267.45 | E20: Employer SS, Medicare, FUTA and AZ SUTA on the owner's wages — a company expense, not his.
B21: K-1 pass-through income to owner | C21: =(C18+C19+C20)*C9 -> 308050.12 | E21: Taxed on the owner's 1040. NOT subject to self-employment or FICA tax.
B23: 3. TAX PARAMETERS (verify before relying on these)
B24: Standard / itemized deduction | C24: 32200 | E24: 2026 standard deduction, MFJ — estimate. Replace with your figure.
B25: Social Security wage base | C25: =Assumptions!$B$20 -> 184500 | E25: 2026: $184,500.
B26: Employee Social Security rate | C26: 0.062
B27: Employee Medicare rate | C27: 0.0145
B28: Additional Medicare rate | C28: 0.009 | E28: Applies to wages above the threshold below.
B29: Additional Medicare threshold | C29: 250000 | E29: $250,000 MFJ / $200,000 single.
B30: Arizona income tax rate | C30: 0.025 | E30: Arizona flat individual rate.
B31: QBI deduction rate | C31: 0.2 | E31: Section 199A.
B32: QBI / SSTB phase-out threshold | C32: 403000 | E32: Accounting is a Specified Service Trade or Business, so the deduction phases out above this. MFJ estimate — verify.
B33: QBI / SSTB phase-out range | C33: 150000 | E33: Fully phased out once taxable income exceeds threshold + range.
B35: 4. FEDERAL BRACKET TABLE (edit to match the final figures)
C36: Bracket floor | D36: Rate | E36: Incremental rate × income above floor (rows sum to the tax)
B37: bracket 1 | C37: 0 | D37: 0.1 | E37: =MAX(0,$C$56-C37)*(D37-0) -> 42229.572
B38: bracket 2 | C38: 24800 | D38: 0.12 | E38: =MAX(0,$C$56-C38)*(D38-D37) -> 7949.9143
B39: bracket 3 | C39: 100800 | D39: 0.22 | E39: =MAX(0,$C$56-C39)*(D39-D38) -> 32149.572
B40: bracket 4 | C40: 211100 | D40: 0.24 | E40: =MAX(0,$C$56-C40)*(D40-D39) -> 4223.9143
B41: bracket 5 | C41: 403000 | D41: 0.32 | E41: =MAX(0,$C$56-C41)*(D41-D40) -> 1543.6573
B42: bracket 6 | C42: 512450 | D42: 0.35 | E42: =MAX(0,$C$56-C42)*(D42-D41) -> 0
B43: bracket 7 | C43: 768700 | D43: 0.37 | E43: =MAX(0,$C$56-C43)*(D43-D42) -> 0
B44: Federal income tax | E44: =SUM(E37:E43) -> 88096.629
B46: 5. OWNER'S TAXABLE INCOME
B47: W-2 salary | C47: =Assumptions!$B$28 -> 184500
B48: K-1 pass-through income | C48: =C21 -> 308050.12
B49: Other household wages | C49: =C10 -> 0
B50: Other household non-wage income | C50: =C11 -> 0
B51: Total income | C51: =C47+C48+C49+C50 -> 492550.12
B52: Less: standard / itemized deduction | C52: =-C24 -> -32200
B53: Taxable income before QBI | C53: =MAX(0,C51+C52) -> 460350.12
B54: QBI phase-out — applicable percentage | C54: =1-MIN(1,MAX(0,(C53-C32)/C33)) -> 0.61766584 | E54: Accounting is an SSTB: 100% means the deduction is fully available, 0% means fully phased out.
B55: QBI deduction | C55: =-MIN(C31*MAX(0,C48)*C54,C31*C53) -> -38054.408 | E55: 20% of qualified business income, reduced by the SSTB phase-out and capped at 20% of taxable income.
B56: TAXABLE INCOME | C56: =MAX(0,C53+C55) -> 422295.72
B58: 6. TOTAL TAX
B59: Federal income tax | C59: =E44 -> 88096.629
B60: Employee Social Security | C60: =C26*MIN(C47,C25) -> 11439 | E60: Withheld from the owner's paycheck. The company separately pays a matching SS and Medicare amount plus FUTA and AZ SUTA — that is the employer tax line in section 2.
B61: Employee Medicare | C61: =C27*C47 -> 2675.25
B62: Additional Medicare | C62: =C28*MAX(0,C47+C49-C29) -> 0 | E62: Wages only. Investment income is outside the Medicare base (that is NIIT territory).
B63: Arizona income tax | C63: =C30*C56 -> 10557.393 | E63: Flat rate applied to federal taxable income — approximate.
B64: TOTAL TAX | C64: =SUM(C59:C63) -> 112768.27
B65: Effective rate on total income | C65: =IF(C51=0,0,C64/C51) -> 0.22894781
B67: 7. CASH TO OWNER
B68: W-2 salary | C68: =C47 -> 184500
B69: K-1 income available to distribute | C69: =C48 -> 308050.12 | E69: Cash only to the extent the firm actually distributes it.
B70: Total pre-tax cash | C70: =C68+C69 -> 492550.12
B71: Less: total tax | C71: =-C64 -> -112768.27
B72: NET AFTER-TAX CASH TO OWNER | C72: =C70+C71 -> 379781.85
B73: Income tax (federal + Arizona) | C73: =C59+C63 -> 98654.022 | E73: Total tax less the FICA already withheld from payroll. This is what estimates must cover.
B74: Quarterly estimated payment | C74: =C73/4 -> 24663.506 | E74: Income tax spread over four quarters. Reduce it by any federal or state income tax already withheld from the owner's salary.
B75: Distribution to cover the tax on K-1 income | C75: =IF(C51=0,0,C73*C48/C51) -> 61700.083 | E75: The K-1's pro-rata share of the income tax — the part the salary does not fund. Keep at least this much distributable so the owner is not paying firm tax out of pocket.
B77: HOW TO READ THIS
B78: • The firm's net income is not the owner's income. Salary is taxed as wages and carries FICA; the rest reaches the 1040 through the K-1 without FICA. That split is the whole point of the S-corp election.
B79: • Setting salary at the Social Security wage base maximises the wages subject to SS while leaving every additional dollar of profit free of it. Above the base only Medicare continues.
B80: • Accounting is a Specified Service Trade or Business, so the 20% QBI deduction phases out as income rises. Watch the applicable percentage in section 5 — at this income level it is partly or entirely gone.
B81: • Raising the owner's salary lowers K-1 income roughly dollar for dollar but adds employer and employee Medicare on the way through, so total tax rises. Lowering it below reasonable compensation invites an IRS challenge.
B82: • State tax is modelled as Arizona's flat rate on federal taxable income. Arizona starts from federal AGI with its own adjustments, so treat this as an approximation.

Sheet Guide
B2: Onyx Accounting Group, LLC
B3: Firm Budget & Forecast — 2026
B4: Updated 2026-08-20 • Jan–Jul actuals + Aug–Dec budget · rates calibrated to actuals · per-person utilization · PEO benefits · growth and hiring
B6: START HERE
B7: Forecast 2026 | C7: The budget: Jan–Jul actual QuickBooks figures, Aug–Dec calculated.
B8: Monthly roll-forward | C8: When a month closes, type its actuals over that month's column on Forecast 2026 and change the band label to ACTUAL.
B9: Utilization | C9: Now PER PERSON, in Monthly Capacity column T. Each cell starts as a link to the firm default on Assumptions!B15 — type over it to make someone custom.
B10: Rate blend method | C10: Assumptions!B36. 1 simple average · 2 hours-weighted · 3 calibrated to actuals (default). The calibration basis is on Bill Rates row 71.
B11: How many hours must Steven bill? | C11: Set Assumptions!B38 to 2, then set the net-income target on Monthly Capacity row 62. Staff capacity is counted first; his hours are the residual.
B13: THE TABS
B14: 1. Bill Rates | C14: Rate per client, with July Harvest hours and billable dollars alongside. Simple average, hours-weighted average, and a calibration to what the firm actually collects.
B15: 2. Assumptions | C15: Hours, PTO, employer tax rates, owner comp, and the four mode switches: rate method (B36), owner hours (B38), bonus factor source (B40).
B16: 3. Staff P&L | C16: Pay, full labour burden, loaded cost per hour and gross profit per person. Also the quarterly bonus block, the operational scorecard and Josephine's pay options.
B17: 4. Benefits | C17: Insperity 1000-Deductible medical by tier under your $338/$676/$1,014 policy, the 401(k) match, and the PEO service fees. Feeds the benefits column on Staff P&L.
B18: 5. Monthly Capacity | C18: Real 2026 calendar to billable hours to revenue, per person. Also the July observed block and the owner residual calculation.
B19: 6. Growth & Hiring | C19: New client revenue and new hires for the rest of the year. Adds straight into the Budget P&L, so Forecast 2026 picks it up Aug–Dec.
B20: 7. Budget P&L | C20: Pure budget, all 12 months. Source of the Aug–Dec figures.
B21: 8. Forecast 2026 | C21: Jan–Jul actual, Aug–Dec budget, plus a pro-forma with all costs expensed.
B22: 9. Owner Earnings | C22: Steven's salary, K-1 pass-through income and the tax that follows.
B24: COLOR LEGEND
B25: Blue on yellow | C25: Input you can change
B26: Green text | C26: Pulled from another tab
B27: Black text | C27: Calculated — do not type over
B28: ACTUAL | C28: Forecast month taken from QuickBooks
B29: BUDGET | C29: Forecast month calculated
B31: KEY OUTPUTS
B32: Total revenue | D32: ='Forecast 2026'!$N$13 -> 1253412.9
B33: Net income (as reported) | D33: ='Forecast 2026'!$N$44 -> 423997.8
B34: Pro-forma net income | D34: ='Forecast 2026'!$N$57 -> 315196.84
B35: Blended bill rate in use | D35: ='Bill Rates'!$H$70*'Bill Rates'!$H$71 -> 156.4198
B36: Realization factor | D36: ='Bill Rates'!$H$71 -> 0.98628503
B37: Utilization — firm default | D37: =Assumptions!$B$15 -> 0.91
B38: Utilization July, model definition | D38: ='Monthly Capacity'!$C$58 -> 0.88353095
B39: Benefits + PEO, full run-rate /yr | D39: =Benefits!$C$53 -> 97268.433
B40: Benefits + PEO landing in 2026 | D40: =Benefits!$C$55 -> 19036.015
B41: Growth: net impact on net income | D41: ='Growth & Hiring'!$N$25 -> 56358.281
B42: Steven's required hours at target | D42: ='Monthly Capacity'!$C$69 -> 1099.4778
B43: Owner K-1 income | D43: ='Owner Earnings'!$C$21 -> 308050.12
B45: OPEN QUESTIONS & SOURCES
B46: • | C46: RATES: weighting the card by client hours changes almost nothing — the card is nearly uniform. The real gap is ROLE MIX. Pull the Harvest Detailed Time Report (person x client x hours) to weight by role properly.
B47: • | C47: UTILIZATION: Harvest's 66% divides by time off and admin and is NOT the model's definition. On the model's own basis July was 88.4%, against 91% assumed, and hours came in at 97% of plan. Do not put 66% in the utilization cell.
B48: • | C48: BENEFITS: tiers on the Benefits tab are a GUESS that reproduces the proposal's census (2 family, 1 spouse, 2 employee-only). Confirm who is on what.
B49: • | C49: PEO: priced on $564,922 of payroll but actual W-2 payroll is higher, so the real service fee will exceed the quoted $88,295. Ask Insperity to re-quote. Start date 25 Oct 2026 means only two months land in 2026.
B50: • | C50: BONUS: do not pay against the 59% invoiced-to-billable figure — it is invoice timing, not write-downs. Actual collections run ABOVE the standard value of logged time.
B51: • | C51: JOSEPHINE: salary and bonus cost exactly the same (7.65% either way). The choice is commitment versus flexibility. At 15% billable she would need a 67% billable share for a $100k salary to pay for itself.
B52: • | C52: Actuals are CASH basis; the budget is accrual. Sources: Harvest July 2026 client report, Insperity HR360 proposal dated 12 Aug 2026, QuickBooks P&L Jan–Jul 2026.
